<statistics DocCount="Number of Treatments" DocUuid="Document UUID" DocDoi="Document DOI" DocArticleUuid="Article UUID" BibYear="Year of Publication" BibSource="Journal / Publisher" BibVolume="Volume" BibIssue="Issue" BibFirstPage="First Page" BibLastPage="Last Page" CitTreatCitCount="Number of Treatment Citations" CitFigCitCount="Number of Figure Citations" CitTabCitCount="Number of Table Citations">
<statData DocCount="1" DocUuid="03D8B2799A3FFFD4FC7AFE101A175403" DocDoi="http://doi.org/10.5281/zenodo.4734662" DocArticleUuid="FFE1CA019A3EFFD6FFC6FC1B1F675359" BibYear="2021" BibSource="Species Diversity" BibVolume="26" BibIssue="1" BibFirstPage="2" BibLastPage="3" CitTreatCitCount="1" CitFigCitCount="16" CitTabCitCount="2"/>
<statData DocCount="1" DocUuid="777CE11D4B64FF89FDE09FB5874AFBF3" DocDoi="http://doi.org/10.5281/zenodo.4562840" DocArticleUuid="8B4599654B67FF93FD779E6E8413FFE2" BibYear="2021" BibSource="Zootaxa" BibVolume="4903" BibIssue="1" BibFirstPage="4" BibLastPage="27" CitTreatCitCount="2" CitFigCitCount="70" CitTabCitCount="20"/>
<statData DocCount="1" DocUuid="153987C4E22DB657D9D254001679FC47" DocDoi="http://doi.org/10.5281/zenodo.4741193" DocArticleUuid="E900FFBCE22BB647D9455063133DFFC6" BibYear="2021" BibSource="Zootaxa" BibVolume="4965" BibIssue="1" BibFirstPage="7" BibLastPage="17" CitTreatCitCount="8" CitFigCitCount="12" CitTabCitCount="4"/>
<statData DocCount="1" DocUuid="2C0487DFFFA5FFDFF7FF5F51015DFB02" DocDoi="http://doi.org/10.5281/zenodo.4683635" DocArticleUuid="D03DFFA7FFA3FFC4F7685E770206FFC7" BibYear="2021" BibSource="Zootaxa" BibVolume="4945" BibIssue="1" BibFirstPage="7" BibLastPage="28" CitTreatCitCount="3" CitFigCitCount="93" CitTabCitCount="6"/>
<statData DocCount="1" DocUuid="038087CBFFE70700FF7592FBFBA0A4AA" DocDoi="http://doi.org/10.5281/zenodo.4683210" DocArticleUuid="FFB9FFB3FFEE070FFFE29409FF89A136" BibYear="2021" BibSource="Zootaxa" BibVolume="4944" BibIssue="1" BibFirstPage="10" BibLastPage="16" CitTreatCitCount="3" CitFigCitCount="37" CitTabCitCount="2"/>
<statData DocCount="1" DocUuid="03D77A7DFFDBF70DFD92D8F5B5DDFB77" DocDoi="http://doi.org/10.5281/zenodo.4680934" DocArticleUuid="FFEE0205FFD1F702FFC4DD3FB117FFCB" BibYear="2021" BibSource="European Journal of Taxonomy" BibVolume="744" BibIssue="0" BibFirstPage="11" BibLastPage="16" CitTreatCitCount="4" CitFigCitCount="20" CitTabCitCount="3"/>
<statData DocCount="1" DocUuid="8545EB45EC04A01EFF3F8FBFFAF083D0" DocDoi="http://doi.org/10.5281/zenodo.4745632" DocArticleUuid="797C933DEC0EA013FFA88F60FFAC8448" BibYear="2021" BibSource="Zootaxa" BibVolume="4969" BibIssue="1" BibFirstPage="11" BibLastPage="14" CitTreatCitCount="5" CitFigCitCount="8" CitTabCitCount="2"/>
<statData DocCount="1" DocUuid="BC53327AFFB16C2A25CFF91BD226C58C" DocDoi="http://doi.org/10.5281/zenodo.4474152" DocArticleUuid="406A4A02FFBA6C362558FFF6D066C458" BibYear="2021" BibSource="Zootaxa" BibVolume="4916" BibIssue="1" BibFirstPage="12" BibLastPage="29" CitTreatCitCount="5" CitFigCitCount="170" CitTabCitCount="4"/>
<statData DocCount="1" DocUuid="A0103577FF8DFFB8FC09D2F27EA806E7" DocDoi="http://doi.org/10.5281/zenodo.4734690" DocArticleUuid="5C294D0FFF8BFFB0FFE7D1017D2A0208" BibYear="2021" BibSource="Species Diversity" BibVolume="26" BibIssue="1" BibFirstPage="13" BibLastPage="17" CitTreatCitCount="12" CitFigCitCount="15" CitTabCitCount="1"/>
<statData DocCount="1" DocUuid="361087A7FFC9FFB255ABF90750ABCDEC" DocDoi="http://doi.org/10.5281/zenodo.4473150" DocArticleUuid="CA29FFDFFFC5FFA0553CFFA5506ACD15" BibYear="2021" BibSource="Zootaxa" BibVolume="4912" BibIssue="1" BibFirstPage="13" BibLastPage="19" CitTreatCitCount="9" CitFigCitCount="36" CitTabCitCount="3"/>
<statData DocCount="1" DocUuid="03BD87E66B6CFFCBAF89FB60FB893EA1" DocDoi="http://doi.org/10.5281/zenodo.4534460" DocArticleUuid="FF84FF9E6B61FFC5AF1EF86AFFDE3D4C" BibYear="2021" BibSource="Zootaxa" BibVolume="4922" BibIssue="1" BibFirstPage="14" BibLastPage="15" CitTreatCitCount="17" CitFigCitCount="2" CitTabCitCount="1"/>
<statData DocCount="1" DocUuid="03BD87E66B6FFFCAAF89FC54FD1E3AD9" DocDoi="http://doi.org/10.5281/zenodo.4534462" DocArticleUuid="FF84FF9E6B61FFC5AF1EF86AFFDE3D4C" BibYear="2021" BibSource="Zootaxa" BibVolume="4922" BibIssue="1" BibFirstPage="15" BibLastPage="16" CitTreatCitCount="15" CitFigCitCount="4" CitTabCitCount="1"/>
<statData DocCount="1" DocUuid="03A41512FFFC4835FC612EFF433801C7" DocDoi="http://doi.org/10.5281/zenodo.4723446" DocArticleUuid="FF9D6D6AFFF24825FF8C2A7447020664" BibYear="2021" BibSource="Journal of Mammalogy" BibVolume="102" BibIssue="2" BibFirstPage="15" BibLastPage="17" CitTreatCitCount="1" CitFigCitCount="19" CitTabCitCount="5"/>
<statData DocCount="1" DocUuid="03D77A7DFFDEF711FD9FD9C5B313FC62" DocDoi="http://doi.org/10.5281/zenodo.4680936" DocArticleUuid="FFEE0205FFD1F702FFC4DD3FB117FFCB" BibYear="2021" BibSource="European Journal of Taxonomy" BibVolume="744" BibIssue="0" BibFirstPage="16" BibLastPage="20" CitTreatCitCount="2" CitFigCitCount="20" CitTabCitCount="2"/>
<statData DocCount="1" DocUuid="03BD87E66B70FFD7AF89F8FDFD1E3C9D" DocDoi="http://doi.org/10.5281/zenodo.4496356" DocArticleUuid="FF84FF9E6B61FFC5AF1EF86AFFDE3D4C" BibYear="2021" BibSource="Zootaxa" BibVolume="4922" BibIssue="1" BibFirstPage="18" BibLastPage="19" CitTreatCitCount="13" CitFigCitCount="5" CitTabCitCount="1"/>
<statData DocCount="1" DocUuid="03BD87E66B73FFD1AF89FA48FD1E3F55" DocDoi="http://doi.org/10.5281/zenodo.4536494" DocArticleUuid="FF84FF9E6B61FFC5AF1EF86AFFDE3D4C" BibYear="2021" BibSource="Zootaxa" BibVolume="4922" BibIssue="1" BibFirstPage="19" BibLastPage="21" CitTreatCitCount="14" CitFigCitCount="6" CitTabCitCount="1"/>
<statData DocCount="1" DocUuid="03D77A7DFFC2F714FE3DD935B27AFAD5" DocDoi="http://doi.org/10.5281/zenodo.4680938" DocArticleUuid="FFEE0205FFD1F702FFC4DD3FB117FFCB" BibYear="2021" BibSource="European Journal of Taxonomy" BibVolume="744" BibIssue="0" BibFirstPage="20" BibLastPage="23" CitTreatCitCount="2" CitFigCitCount="24" CitTabCitCount="1"/>
<statData DocCount="1" DocUuid="03BD87E66B74FFD2AF89FC0DFD1E3F2D" DocDoi="http://doi.org/10.5281/zenodo.4534468" DocArticleUuid="FF84FF9E6B61FFC5AF1EF86AFFDE3D4C" BibYear="2021" BibSource="Zootaxa" BibVolume="4922" BibIssue="1" BibFirstPage="22" BibLastPage="24" CitTreatCitCount="17" CitFigCitCount="4" CitTabCitCount="1"/>
<statData DocCount="1" DocUuid="03D77A7DFFC7F718FDD7D89DB203FD6A" DocDoi="http://doi.org/10.5281/zenodo.4680940" DocArticleUuid="FFEE0205FFD1F702FFC4DD3FB117FFCB" BibYear="2021" BibSource="European Journal of Taxonomy" BibVolume="744" BibIssue="0" BibFirstPage="23" BibLastPage="27" CitTreatCitCount="4" CitFigCitCount="16" CitTabCitCount="2"/>
<statData DocCount="1" DocUuid="361087A7FFD3FFBA55ABFECB5455CA6E" DocDoi="http://doi.org/10.5281/zenodo.4473158" DocArticleUuid="CA29FFDFFFC5FFA0553CFFA5506ACD15" BibYear="2021" BibSource="Zootaxa" BibVolume="4912" BibIssue="1" BibFirstPage="23" BibLastPage="27" CitTreatCitCount="7" CitFigCitCount="30" CitTabCitCount="4"/>
<statData DocCount="1" DocUuid="8545EB45EC18A008FF3F8A1FFD5A8555" DocDoi="http://doi.org/10.5281/zenodo.4745643" DocArticleUuid="797C933DEC0EA013FFA88F60FFAC8448" BibYear="2021" BibSource="Zootaxa" BibVolume="4969" BibIssue="1" BibFirstPage="23" BibLastPage="27" CitTreatCitCount="5" CitFigCitCount="9" CitTabCitCount="1"/>
<statData DocCount="1" DocUuid="153987C4E23CB65DD9D250F41712FEDB" DocDoi="http://doi.org/10.5281/zenodo.4741197" DocArticleUuid="E900FFBCE22BB647D9455063133DFFC6" BibYear="2021" BibSource="Zootaxa" BibVolume="4965" BibIssue="1" BibFirstPage="24" BibLastPage="27" CitTreatCitCount="2" CitFigCitCount="3" CitTabCitCount="5"/>
<statData DocCount="1" DocUuid="03BD87E66B78FFDFAF89FBF4FD1E3E59" DocDoi="http://doi.org/10.5281/zenodo.4496364" DocArticleUuid="FF84FF9E6B61FFC5AF1EF86AFFDE3D4C" BibYear="2021" BibSource="Zootaxa" BibVolume="4922" BibIssue="1" BibFirstPage="26" BibLastPage="27" CitTreatCitCount="10" CitFigCitCount="4" CitTabCitCount="1"/>
<statData DocCount="1" DocUuid="03D77A7DFFCBF71EFDC3DFE0B0E0FBC5" DocDoi="http://doi.org/10.5281/zenodo.4680943" DocArticleUuid="FFEE0205FFD1F702FFC4DD3FB117FFCB" BibYear="2021" BibSource="European Journal of Taxonomy" BibVolume="744" BibIssue="0" BibFirstPage="27" BibLastPage="29" CitTreatCitCount="2" CitFigCitCount="15" CitTabCitCount="1"/>
<statData DocCount="1" DocUuid="03BD87E66B7BFFD9AF89FDA4FD1E39ED" DocDoi="http://doi.org/10.5281/zenodo.4534475" DocArticleUuid="FF84FF9E6B61FFC5AF1EF86AFFDE3D4C" BibYear="2021" BibSource="Zootaxa" BibVolume="4922" BibIssue="1" BibFirstPage="27" BibLastPage="29" CitTreatCitCount="3" CitFigCitCount="4" CitTabCitCount="1"/>
<statData DocCount="1" DocUuid="DA028789FE1BFF87FF4A5329FB0FFE92" DocDoi="http://doi.org/10.5281/zenodo.4710261" DocArticleUuid="263BFFF1FE1FFF8EFFDD502CFFADFF8E" BibYear="2021" BibSource="Zootaxa" BibVolume="4949" BibIssue="1" BibFirstPage="28" BibLastPage="32" CitTreatCitCount="16" CitFigCitCount="26" CitTabCitCount="6"/>
<statData DocCount="1" DocUuid="BC53327AFFA66C1625CFFDECD119C7B5" DocDoi="http://doi.org/10.5281/zenodo.4474154" DocArticleUuid="406A4A02FFBA6C362558FFF6D066C458" BibYear="2021" BibSource="Zootaxa" BibVolume="4916" BibIssue="1" BibFirstPage="29" BibLastPage="31" CitTreatCitCount="2" CitFigCitCount="7" CitTabCitCount="1"/>
<statData DocCount="1" DocUuid="03BD87E66B7CFFDBAF89FE25FD1E3A49" DocDoi="http://doi.org/10.5281/zenodo.4560692" DocArticleUuid="FF84FF9E6B61FFC5AF1EF86AFFDE3D4C" BibYear="2021" BibSource="Zootaxa" BibVolume="4922" BibIssue="1" BibFirstPage="30" BibLastPage="31" CitTreatCitCount="7" CitFigCitCount="4" CitTabCitCount="1"/>
<statData DocCount="1" DocUuid="C10A5544FF80FFA1151CA5B3FC2AFC8A" DocDoi="http://doi.org/10.5281/zenodo.4737622" DocArticleUuid="3D332D3CFF8FFFB0177CA434F970FFE8" BibYear="2021" BibSource="European Journal of Taxonomy" BibVolume="748" BibIssue="1" BibFirstPage="30" BibLastPage="32" CitTreatCitCount="3" CitFigCitCount="17" CitTabCitCount="1"/>
<statData DocCount="1" DocUuid="335587B2C4761C2BFF28FC88FDFEFD14" DocDoi="http://doi.org/10.5281/zenodo.4474375" DocArticleUuid="CF6CFFCAC4571C0EFFBFFA70FFE5FFD9" BibYear="2021" BibSource="Zootaxa" BibVolume="4918" BibIssue="1" BibFirstPage="34" BibLastPage="38" CitTreatCitCount="7" CitFigCitCount="3" CitTabCitCount="3"/>
<statData DocCount="1" DocUuid="035E87B2FF92FFBDFF0230DCFC6FD0B7" DocDoi="http://doi.org/10.5281/zenodo.4448751" DocArticleUuid="FF67FFCAFFB0FF9EFF953571FFBBD142" BibYear="2021" BibSource="Zootaxa" BibVolume="4909" BibIssue="1" BibFirstPage="35" BibLastPage="36" CitTreatCitCount="1" CitFigCitCount="2" CitTabCitCount="1"/>
<statData DocCount="1" DocUuid="03A6D248FFBF8B65DEC1F9FAFD78D1AA" DocDoi="http://doi.org/10.5281/zenodo.4602467" DocArticleUuid="FF9FAA30FF9C8B52DF38FFAFFFC3D05C" BibYear="2021" BibSource="European Journal of Taxonomy" BibVolume="737" BibIssue="1" BibFirstPage="36" BibLastPage="55" CitTreatCitCount="9" CitFigCitCount="29" CitTabCitCount="4"/>
<statData DocCount="1" DocUuid="038487E62F05241DFF12B589FD88FDCE" DocDoi="http://doi.org/10.5281/zenodo.4771787" DocArticleUuid="FFBDFF9E2F20243AFF85B51EFF9BFFD8" BibYear="2021" BibSource="Zootaxa" BibVolume="4973" BibIssue="1" BibFirstPage="38" BibLastPage="40" CitTreatCitCount="1" CitFigCitCount="6" CitTabCitCount="1"/>
<statData DocCount="1" DocUuid="335587B2C4721C23FF28FD6AFC3BF9BA" DocDoi="http://doi.org/10.5281/zenodo.4474377" DocArticleUuid="CF6CFFCAC4571C0EFFBFFA70FFE5FFD9" BibYear="2021" BibSource="Zootaxa" BibVolume="4918" BibIssue="1" BibFirstPage="38" BibLastPage="46" CitTreatCitCount="4" CitFigCitCount="8" CitTabCitCount="5"/>
<statData DocCount="1" DocUuid="BC53327AFF9C6C1F25CFFCE9D119C275" DocDoi="http://doi.org/10.5281/zenodo.4474162" DocArticleUuid="406A4A02FFBA6C362558FFF6D066C458" BibYear="2021" BibSource="Zootaxa" BibVolume="4916" BibIssue="1" BibFirstPage="39" BibLastPage="41" CitTreatCitCount="2" CitFigCitCount="5" CitTabCitCount="1"/>
<statData DocCount="1" DocUuid="03BD87E66B48FFEEAF89FF78FD1E3BAD" DocDoi="http://doi.org/10.5281/zenodo.4560698" DocArticleUuid="FF84FF9E6B61FFC5AF1EF86AFFDE3D4C" BibYear="2021" BibSource="Zootaxa" BibVolume="4922" BibIssue="1" BibFirstPage="42" BibLastPage="44" CitTreatCitCount="10" CitFigCitCount="4" CitTabCitCount="1"/>
<statData DocCount="1" DocUuid="BC53327AFF936C1A25CFF989D296C705" DocDoi="http://doi.org/10.5281/zenodo.4467522" DocArticleUuid="406A4A02FFBA6C362558FFF6D066C458" BibYear="2021" BibSource="Zootaxa" BibVolume="4916" BibIssue="1" BibFirstPage="42" BibLastPage="45" CitTreatCitCount="3" CitFigCitCount="8" CitTabCitCount="1"/>
<statData DocCount="1" DocUuid="8545EB45EC27A03EFF3F8E9EFCB482A4" DocDoi="http://doi.org/10.5281/zenodo.4745649" DocArticleUuid="797C933DEC0EA013FFA88F60FFAC8448" BibYear="2021" BibSource="Zootaxa" BibVolume="4969" BibIssue="1" BibFirstPage="42" BibLastPage="46" CitTreatCitCount="3" CitFigCitCount="9" CitTabCitCount="1"/>
<statData DocCount="1" DocUuid="335587B2C47A1C20FF28FCC3FD96F807" DocDoi="http://doi.org/10.5281/zenodo.4474379" DocArticleUuid="CF6CFFCAC4571C0EFFBFFA70FFE5FFD9" BibYear="2021" BibSource="Zootaxa" BibVolume="4918" BibIssue="1" BibFirstPage="46" BibLastPage="47" CitTreatCitCount="2" CitFigCitCount="5" CitTabCitCount="3"/>
<statData DocCount="1" DocUuid="03BD87E66B4EFFF4AF89F8FDFD1E3B1D" DocDoi="http://doi.org/10.5281/zenodo.4534492" DocArticleUuid="FF84FF9E6B61FFC5AF1EF86AFFDE3D4C" BibYear="2021" BibSource="Zootaxa" BibVolume="4922" BibIssue="1" BibFirstPage="48" BibLastPage="50" CitTreatCitCount="7" CitFigCitCount="4" CitTabCitCount="1"/>
<statData DocCount="1" DocUuid="BC53327AFF8A6C0525CFFF61D2ACC2B9" DocDoi="http://doi.org/10.5281/zenodo.4474165" DocArticleUuid="406A4A02FFBA6C362558FFF6D066C458" BibYear="2021" BibSource="Zootaxa" BibVolume="4916" BibIssue="1" BibFirstPage="49" BibLastPage="51" CitTreatCitCount="5" CitFigCitCount="5" CitTabCitCount="1"/>
<statData DocCount="1" DocUuid="335587B2C4651C3CFF28FAE7FAA8FBDB" DocDoi="http://doi.org/10.5281/zenodo.4474381" DocArticleUuid="CF6CFFCAC4571C0EFFBFFA70FFE5FFD9" BibYear="2021" BibSource="Zootaxa" BibVolume="4918" BibIssue="1" BibFirstPage="51" BibLastPage="51" CitTreatCitCount="2" CitFigCitCount="2" CitTabCitCount="3"/>
<statData DocCount="1" DocUuid="03BD87E66B53FFF0AF89FF64FD1E395D" DocDoi="http://doi.org/10.5281/zenodo.4560700" DocArticleUuid="FF84FF9E6B61FFC5AF1EF86AFFDE3D4C" BibYear="2021" BibSource="Zootaxa" BibVolume="4922" BibIssue="1" BibFirstPage="51" BibLastPage="54" CitTreatCitCount="17" CitFigCitCount="4" CitTabCitCount="1"/>
<statData DocCount="1" DocUuid="361087A7FFF6FF9555ABFEEF5223CC9C" DocDoi="http://doi.org/10.5281/zenodo.4473184" DocArticleUuid="CA29FFDFFFC5FFA0553CFFA5506ACD15" BibYear="2021" BibSource="Zootaxa" BibVolume="4912" BibIssue="1" BibFirstPage="52" BibLastPage="54" CitTreatCitCount="11" CitFigCitCount="1" CitTabCitCount="1"/>
<statData DocCount="1" DocUuid="03BD87E66B54FFF2AF89FC08FD1E3A91" DocDoi="http://doi.org/10.5281/zenodo.4537697" DocArticleUuid="FF84FF9E6B61FFC5AF1EF86AFFDE3D4C" BibYear="2021" BibSource="Zootaxa" BibVolume="4922" BibIssue="1" BibFirstPage="54" BibLastPage="56" CitTreatCitCount="24" CitFigCitCount="4" CitTabCitCount="1"/>
<statData DocCount="1" DocUuid="BC53327AFF826C0D25CFF91DD32AC6A9" DocDoi="http://doi.org/10.5281/zenodo.4474171" DocArticleUuid="406A4A02FFBA6C362558FFF6D066C458" BibYear="2021" BibSource="Zootaxa" BibVolume="4916" BibIssue="1" BibFirstPage="57" BibLastPage="60" CitTreatCitCount="1" CitFigCitCount="6" CitTabCitCount="1"/>
<statData DocCount="1" DocUuid="335587B2C46D1C35FF28FC77FE26F8B3" DocDoi="http://doi.org/10.5281/zenodo.4474385" DocArticleUuid="CF6CFFCAC4571C0EFFBFFA70FFE5FFD9" BibYear="2021" BibSource="Zootaxa" BibVolume="4918" BibIssue="1" BibFirstPage="59" BibLastPage="60" CitTreatCitCount="7" CitFigCitCount="3" CitTabCitCount="3"/>
<statData DocCount="1" DocUuid="BC53327AFF816C0825CFFCC0D3FAC169" DocDoi="http://doi.org/10.5281/zenodo.4474175" DocArticleUuid="406A4A02FFBA6C362558FFF6D066C458" BibYear="2021" BibSource="Zootaxa" BibVolume="4916" BibIssue="1" BibFirstPage="60" BibLastPage="62" CitTreatCitCount="3" CitFigCitCount="7" CitTabCitCount="1"/>
<statData DocCount="1" DocUuid="03A6D248FFA78B11DECBFDFDFD6ED3A0" DocDoi="http://doi.org/10.5281/zenodo.4602471" DocArticleUuid="FF9FAA30FF9C8B52DF38FFAFFFC3D05C" BibYear="2021" BibSource="European Journal of Taxonomy" BibVolume="737" BibIssue="1" BibFirstPage="60" BibLastPage="68" CitTreatCitCount="2" CitFigCitCount="10" CitTabCitCount="2"/>
<statData DocCount="1" DocUuid="03BD87E66B5FFF85AF89FACDFD1E3EA1" DocDoi="http://doi.org/10.5281/zenodo.4560702" DocArticleUuid="FF84FF9E6B61FFC5AF1EF86AFFDE3D4C" BibYear="2021" BibSource="Zootaxa" BibVolume="4922" BibIssue="1" BibFirstPage="63" BibLastPage="65" CitTreatCitCount="16" CitFigCitCount="3" CitTabCitCount="1"/>
<statData DocCount="1" DocUuid="361087A7FFFAFFE555ABF9FF51BECDEC" DocDoi="http://doi.org/10.5281/zenodo.4473190" DocArticleUuid="CA29FFDFFFC5FFA0553CFFA5506ACD15" BibYear="2021" BibSource="Zootaxa" BibVolume="4912" BibIssue="1" BibFirstPage="64" BibLastPage="70" CitTreatCitCount="7" CitFigCitCount="15" CitTabCitCount="2"/>
<statData DocCount="1" DocUuid="335587B2C4171C4CFF28F932FD54FF0C" DocDoi="http://doi.org/10.5281/zenodo.4474391" DocArticleUuid="CF6CFFCAC4571C0EFFBFFA70FFE5FFD9" BibYear="2021" BibSource="Zootaxa" BibVolume="4918" BibIssue="1" BibFirstPage="65" BibLastPage="66" CitTreatCitCount="6" CitFigCitCount="5" CitTabCitCount="3"/>
<statData DocCount="1" DocUuid="03BD87E66B21FF84AF89FCC1FD1E3B45" DocDoi="http://doi.org/10.5281/zenodo.4496440" DocArticleUuid="FF84FF9E6B61FFC5AF1EF86AFFDE3D4C" BibYear="2021" BibSource="Zootaxa" BibVolume="4922" BibIssue="1" BibFirstPage="65" BibLastPage="66" CitTreatCitCount="3" CitFigCitCount="3" CitTabCitCount="1"/>
<statData DocCount="1" DocUuid="BC53327AFFFA6C7525CFFC01D42BC6F1" DocDoi="http://doi.org/10.5281/zenodo.4474177" DocArticleUuid="406A4A02FFBA6C362558FFF6D066C458" BibYear="2021" BibSource="Zootaxa" BibVolume="4916" BibIssue="1" BibFirstPage="65" BibLastPage="67" CitTreatCitCount="1" CitFigCitCount="4" CitTabCitCount="1"/>
<statData DocCount="1" DocUuid="335587B2C4151C4DFF28FED7FEC2FD70" DocDoi="http://doi.org/10.5281/zenodo.4474393" DocArticleUuid="CF6CFFCAC4571C0EFFBFFA70FFE5FFD9" BibYear="2021" BibSource="Zootaxa" BibVolume="4918" BibIssue="1" BibFirstPage="67" BibLastPage="68" CitTreatCitCount="12" CitFigCitCount="4" CitTabCitCount="3"/>
<statData DocCount="1" DocUuid="BC53327AFFF96C7025CFFD18D4ECC001" DocDoi="http://doi.org/10.5281/zenodo.4474179" DocArticleUuid="406A4A02FFBA6C362558FFF6D066C458" BibYear="2021" BibSource="Zootaxa" BibVolume="4916" BibIssue="1" BibFirstPage="68" BibLastPage="70" CitTreatCitCount="2" CitFigCitCount="11" CitTabCitCount="1"/>
<statData DocCount="1" DocUuid="335587B2C4141C49FF28FFEEFB79FF20" DocDoi="http://doi.org/10.5281/zenodo.4474395" DocArticleUuid="CF6CFFCAC4571C0EFFBFFA70FFE5FFD9" BibYear="2021" BibSource="Zootaxa" BibVolume="4918" BibIssue="1" BibFirstPage="68" BibLastPage="71" CitTreatCitCount="4" CitFigCitCount="10" CitTabCitCount="3"/>
<statData DocCount="1" DocUuid="03A6D248FFDF8B1FDD74FB95FC9DD2FD" DocDoi="http://doi.org/10.5281/zenodo.4602473" DocArticleUuid="FF9FAA30FF9C8B52DF38FFAFFFC3D05C" BibYear="2021" BibSource="European Journal of Taxonomy" BibVolume="737" BibIssue="1" BibFirstPage="68" BibLastPage="78" CitTreatCitCount="12" CitFigCitCount="15" CitTabCitCount="5"/>
<statData DocCount="1" DocUuid="03BD87E66B25FF83AF89FD84FD1E38D1" DocDoi="http://doi.org/10.5281/zenodo.4534507" DocArticleUuid="FF84FF9E6B61FFC5AF1EF86AFFDE3D4C" BibYear="2021" BibSource="Zootaxa" BibVolume="4922" BibIssue="1" BibFirstPage="69" BibLastPage="71" CitTreatCitCount="4" CitFigCitCount="2" CitTabCitCount="1"/>
<statData DocCount="1" DocUuid="D5365613DD035D484B22FD9FFC7709EC" DocDoi="http://doi.org/10.5281/zenodo.4681774" DocArticleUuid="290F2E6BDD075D4F4A75FF89FFCC085D" BibYear="2021" BibSource="Adansonia" BibVolume="43" BibIssue="8" BibFirstPage="69" BibLastPage="72" CitTreatCitCount="3" CitFigCitCount="5" CitTabCitCount="3"/>
<statData DocCount="1" DocUuid="03BD87E66B27FF8DAF89FD84FD1E3F55" DocDoi="http://doi.org/10.5281/zenodo.4534509" DocArticleUuid="FF84FF9E6B61FFC5AF1EF86AFFDE3D4C" BibYear="2021" BibSource="Zootaxa" BibVolume="4922" BibIssue="1" BibFirstPage="71" BibLastPage="73" CitTreatCitCount="2" CitFigCitCount="4" CitTabCitCount="1"/>
<statData DocCount="1" DocUuid="BC53327AFFFC6C7F25CFFB5DD09DC121" DocDoi="http://doi.org/10.5281/zenodo.4474181" DocArticleUuid="406A4A02FFBA6C362558FFF6D066C458" BibYear="2021" BibSource="Zootaxa" BibVolume="4916" BibIssue="1" BibFirstPage="71" BibLastPage="74" CitTreatCitCount="1" CitFigCitCount="6" CitTabCitCount="1"/>
<statData DocCount="1" DocUuid="335587B2C4101C42FF28FE21FD41FDC0" DocDoi="http://doi.org/10.5281/zenodo.4474397" DocArticleUuid="CF6CFFCAC4571C0EFFBFFA70FFE5FFD9" BibYear="2021" BibSource="Zootaxa" BibVolume="4918" BibIssue="1" BibFirstPage="72" BibLastPage="77" CitTreatCitCount="11" CitFigCitCount="2" CitTabCitCount="3"/>
<statData DocCount="1" DocUuid="03BD87E66B29FF8CAF89FA00FD1E389F" DocDoi="http://doi.org/10.5281/zenodo.4560704" DocArticleUuid="FF84FF9E6B61FFC5AF1EF86AFFDE3D4C" BibYear="2021" BibSource="Zootaxa" BibVolume="4922" BibIssue="1" BibFirstPage="73" BibLastPage="74" CitTreatCitCount="7" CitFigCitCount="4" CitTabCitCount="1"/>
<statData DocCount="1" DocUuid="03BD87E66B28FF8EAF89FE7DFD1E3CC5" DocDoi="http://doi.org/10.5281/zenodo.4560706" DocArticleUuid="FF84FF9E6B61FFC5AF1EF86AFFDE3D4C" BibYear="2021" BibSource="Zootaxa" BibVolume="4922" BibIssue="1" BibFirstPage="74" BibLastPage="76" CitTreatCitCount="20" CitFigCitCount="4" CitTabCitCount="1"/>
<statData DocCount="1" DocUuid="03BD87E66B2AFF88AF89F9A5FD1E3EE9" DocDoi="http://doi.org/10.5281/zenodo.4560708" DocArticleUuid="FF84FF9E6B61FFC5AF1EF86AFFDE3D4C" BibYear="2021" BibSource="Zootaxa" BibVolume="4922" BibIssue="1" BibFirstPage="76" BibLastPage="78" CitTreatCitCount="8" CitFigCitCount="4" CitTabCitCount="1"/>
<statData DocCount="1" DocUuid="463D87FC3262DD2AFDF3FCE5A1207337" DocDoi="http://doi.org/10.5281/zenodo.4746362" DocArticleUuid="BA04FF84326BDD27FFD1FFD8A5637420" BibYear="2021" BibSource="European Journal of Taxonomy" BibVolume="748" BibIssue="1" BibFirstPage="76" BibLastPage="80" CitTreatCitCount="1" CitFigCitCount="14" CitTabCitCount="1"/>
<statData DocCount="1" DocUuid="BC53327AFFF66C6725CFFF61D1D6C209" DocDoi="http://doi.org/10.5281/zenodo.4474183" DocArticleUuid="406A4A02FFBA6C362558FFF6D066C458" BibYear="2021" BibSource="Zootaxa" BibVolume="4916" BibIssue="1" BibFirstPage="77" BibLastPage="79" CitTreatCitCount="9" CitFigCitCount="10" CitTabCitCount="1"/>
<statData DocCount="1" DocUuid="335587B2C41B1C41FF28F81AFEEEFEC4" DocDoi="http://doi.org/10.5281/zenodo.4474399" DocArticleUuid="CF6CFFCAC4571C0EFFBFFA70FFE5FFD9" BibYear="2021" BibSource="Zootaxa" BibVolume="4918" BibIssue="1" BibFirstPage="77" BibLastPage="79" CitTreatCitCount="7" CitFigCitCount="10" CitTabCitCount="3"/>
<statData DocCount="1" DocUuid="03BD87E66B2CFF8BAF89FB81FD1E39ED" DocDoi="http://doi.org/10.5281/zenodo.4534511" DocArticleUuid="FF84FF9E6B61FFC5AF1EF86AFFDE3D4C" BibYear="2021" BibSource="Zootaxa" BibVolume="4922" BibIssue="1" BibFirstPage="78" BibLastPage="79" CitTreatCitCount="5" CitFigCitCount="4" CitTabCitCount="1"/>
<statData DocCount="1" DocUuid="03A6D248FFD18B05DEDFFD70FB78D369" DocDoi="http://doi.org/10.5281/zenodo.4602475" DocArticleUuid="FF9FAA30FF9C8B52DF38FFAFFFC3D05C" BibYear="2021" BibSource="European Journal of Taxonomy" BibVolume="737" BibIssue="1" BibFirstPage="78" BibLastPage="88" CitTreatCitCount="1" CitFigCitCount="16" CitTabCitCount="2"/>
<statData DocCount="1" DocUuid="03BD87E66B2FFF8BAF89FC8DFD1E3A42" DocDoi="http://doi.org/10.5281/zenodo.4534513" DocArticleUuid="FF84FF9E6B61FFC5AF1EF86AFFDE3D4C" BibYear="2021" BibSource="Zootaxa" BibVolume="4922" BibIssue="1" BibFirstPage="79" BibLastPage="79" CitTreatCitCount="1" CitFigCitCount="2" CitTabCitCount="1"/>
<statData DocCount="1" DocUuid="335587B2C4181C5EFF28FB1EFF32FC42" DocDoi="http://doi.org/10.5281/zenodo.4474401" DocArticleUuid="CF6CFFCAC4571C0EFFBFFA70FFE5FFD9" BibYear="2021" BibSource="Zootaxa" BibVolume="4918" BibIssue="1" BibFirstPage="80" BibLastPage="81" CitTreatCitCount="7" CitFigCitCount="1" CitTabCitCount="4"/>
<statData DocCount="1" DocUuid="03BD87E66B31FF94AF89FF58FD1E3DB5" DocDoi="http://doi.org/10.5281/zenodo.4496450" DocArticleUuid="FF84FF9E6B61FFC5AF1EF86AFFDE3D4C" BibYear="2021" BibSource="Zootaxa" BibVolume="4922" BibIssue="1" BibFirstPage="81" BibLastPage="82" CitTreatCitCount="1" CitFigCitCount="2" CitTabCitCount="1"/>
<statData DocCount="1" DocUuid="335587B2C4071C58FF28F992FA76FB80" DocDoi="http://doi.org/10.5281/zenodo.4474403" DocArticleUuid="CF6CFFCAC4571C0EFFBFFA70FFE5FFD9" BibYear="2021" BibSource="Zootaxa" BibVolume="4918" BibIssue="1" BibFirstPage="81" BibLastPage="87" CitTreatCitCount="6" CitFigCitCount="4" CitTabCitCount="4"/>
<statData DocCount="1" DocUuid="03BD87E66B34FF92AF89F9B0FD1E3C29" DocDoi="http://doi.org/10.5281/zenodo.4496468" DocArticleUuid="FF84FF9E6B61FFC5AF1EF86AFFDE3D4C" BibYear="2021" BibSource="Zootaxa" BibVolume="4922" BibIssue="1" BibFirstPage="86" BibLastPage="88" CitTreatCitCount="1" CitFigCitCount="4" CitTabCitCount="1"/>
<statData DocCount="1" DocUuid="BC53327AFFEC6C6E25CFFC59D51FC3A4" DocDoi="http://doi.org/10.5281/zenodo.4474187" DocArticleUuid="406A4A02FFBA6C362558FFF6D066C458" BibYear="2021" BibSource="Zootaxa" BibVolume="4916" BibIssue="1" BibFirstPage="87" BibLastPage="89" CitTreatCitCount="1" CitFigCitCount="5" CitTabCitCount="1"/>
<statData DocCount="1" DocUuid="335587B2C4011C56FF28FEDAFEFFFC7C" DocDoi="http://doi.org/10.5281/zenodo.4467683" DocArticleUuid="CF6CFFCAC4571C0EFFBFFA70FFE5FFD9" BibYear="2021" BibSource="Zootaxa" BibVolume="4918" BibIssue="1" BibFirstPage="87" BibLastPage="89" CitTreatCitCount="2" CitFigCitCount="4" CitTabCitCount="3"/>
<statData DocCount="1" DocUuid="03BD87E66B36FF9DAF89F9DCFD1E3A3D" DocDoi="http://doi.org/10.5281/zenodo.4534520" DocArticleUuid="FF84FF9E6B61FFC5AF1EF86AFFDE3D4C" BibYear="2021" BibSource="Zootaxa" BibVolume="4922" BibIssue="1" BibFirstPage="88" BibLastPage="89" CitTreatCitCount="3" CitFigCitCount="4" CitTabCitCount="1"/>
<statData DocCount="1" DocUuid="F0537A31FFF44A32FF3B8B597BBAF9B4" DocDoi="http://doi.org/10.5281/zenodo.4549213" DocArticleUuid="0C6A0249FFF54A34FFAC8F3B7A3AFFE5" BibYear="2021" BibSource="Zootaxa" BibVolume="4927" BibIssue="1" BibFirstPage="88" BibLastPage="93" CitTreatCitCount="1" CitFigCitCount="12" CitTabCitCount="2"/>
<statData DocCount="1" DocUuid="03A6D248FFCB8B0DDECDFC2DFC66D305" DocDoi="http://doi.org/10.5281/zenodo.4602477" DocArticleUuid="FF9FAA30FF9C8B52DF38FFAFFFC3D05C" BibYear="2021" BibSource="European Journal of Taxonomy" BibVolume="737" BibIssue="1" BibFirstPage="88" BibLastPage="96" CitTreatCitCount="5" CitFigCitCount="15" CitTabCitCount="2"/>
<statData DocCount="1" DocUuid="335587B2C40F1C52FF28F986FD2AFCE0" DocDoi="http://doi.org/10.5281/zenodo.4474405" DocArticleUuid="CF6CFFCAC4571C0EFFBFFA70FFE5FFD9" BibYear="2021" BibSource="Zootaxa" BibVolume="4918" BibIssue="1" BibFirstPage="89" BibLastPage="93" CitTreatCitCount="3" CitFigCitCount="6" CitTabCitCount="6"/>
<statData DocCount="1" DocUuid="03BD87E66B38FF9CAF89F8FDFD1E3F29" DocDoi="http://doi.org/10.5281/zenodo.4560710" DocArticleUuid="FF84FF9E6B61FFC5AF1EF86AFFDE3D4C" BibYear="2021" BibSource="Zootaxa" BibVolume="4922" BibIssue="1" BibFirstPage="90" BibLastPage="90" CitTreatCitCount="9" CitFigCitCount="2" CitTabCitCount="1"/>
<statData DocCount="1" DocUuid="BC53327AFFE36C6D25CFFF61D160C3D4" DocDoi="http://doi.org/10.5281/zenodo.4474189" DocArticleUuid="406A4A02FFBA6C362558FFF6D066C458" BibYear="2021" BibSource="Zootaxa" BibVolume="4916" BibIssue="1" BibFirstPage="90" BibLastPage="92" CitTreatCitCount="4" CitFigCitCount="7" CitTabCitCount="1"/>
<statData DocCount="1" DocUuid="03BD87E66B38FF9EAF89FDB3FD1E3B61" DocDoi="http://doi.org/10.5281/zenodo.4534526" DocArticleUuid="FF84FF9E6B61FFC5AF1EF86AFFDE3D4C" BibYear="2021" BibSource="Zootaxa" BibVolume="4922" BibIssue="1" BibFirstPage="90" BibLastPage="92" CitTreatCitCount="1" CitFigCitCount="4" CitTabCitCount="1"/>
<statData DocCount="1" DocUuid="03CA87A4D360803079234572FAAC616E" DocDoi="http://doi.org/10.5281/zenodo.4644412" DocArticleUuid="FFF3FFDCD3708022781D441FFFC86728" BibYear="2021" BibSource="European Journal of Taxonomy" BibVolume="740" BibIssue="1" BibFirstPage="93" BibLastPage="95" CitTreatCitCount="3" CitFigCitCount="10" CitTabCitCount="1"/>
<statData DocCount="1" DocUuid="03BD87E66B3DFF9BAF89FF58FD1E3BAD" DocDoi="http://doi.org/10.5281/zenodo.4534530" DocArticleUuid="FF84FF9E6B61FFC5AF1EF86AFFDE3D4C" BibYear="2021" BibSource="Zootaxa" BibVolume="4922" BibIssue="1" BibFirstPage="93" BibLastPage="95" CitTreatCitCount="3" CitFigCitCount="4" CitTabCitCount="1"/>
<statData DocCount="1" DocUuid="F0537A31FFF34A3BFF3B89997B31FC40" DocDoi="http://doi.org/10.5281/zenodo.4549215" DocArticleUuid="0C6A0249FFF54A34FFAC8F3B7A3AFFE5" BibYear="2021" BibSource="Zootaxa" BibVolume="4927" BibIssue="1" BibFirstPage="93" BibLastPage="102" CitTreatCitCount="1" CitFigCitCount="10" CitTabCitCount="1"/>
<statData DocCount="1" DocUuid="335587B2C4091C6EFF28F92BFB23FEC4" DocDoi="http://doi.org/10.5281/zenodo.4474409" DocArticleUuid="CF6CFFCAC4571C0EFFBFFA70FFE5FFD9" BibYear="2021" BibSource="Zootaxa" BibVolume="4918" BibIssue="1" BibFirstPage="95" BibLastPage="96" CitTreatCitCount="11" CitFigCitCount="5" CitTabCitCount="3"/>
<statData DocCount="1" DocUuid="03A6D248FFC38B34DD73FC0AFC14D373" DocDoi="http://doi.org/10.5281/zenodo.4602479" DocArticleUuid="FF9FAA30FF9C8B52DF38FFAFFFC3D05C" BibYear="2021" BibSource="European Journal of Taxonomy" BibVolume="737" BibIssue="1" BibFirstPage="96" BibLastPage="103" CitTreatCitCount="7" CitFigCitCount="8" CitTabCitCount="2"/>
<statData DocCount="1" DocUuid="335587B2C4371C6FFF28FB1EFA78F87C" DocDoi="http://doi.org/10.5281/zenodo.4474411" DocArticleUuid="CF6CFFCAC4571C0EFFBFFA70FFE5FFD9" BibYear="2021" BibSource="Zootaxa" BibVolume="4918" BibIssue="1" BibFirstPage="97" BibLastPage="98" CitTreatCitCount="7" CitFigCitCount="7" CitTabCitCount="3"/>
<statData DocCount="1" DocUuid="03F787DF1D08D96CFD946BBA87B6FA8C" DocDoi="http://doi.org/10.5281/zenodo.4615161" DocArticleUuid="FFCEFFA71D0DD960FF886D158538FF88" BibYear="2021" BibSource="European Journal of Taxonomy" BibVolume="739" BibIssue="1" BibFirstPage="97" BibLastPage="104" CitTreatCitCount="2" CitFigCitCount="23" CitTabCitCount="1"/>
<statData DocCount="1" DocUuid="883287E0FFC89575CE3CA185FC052EBB" DocDoi="http://doi.org/10.5281/zenodo.4709915" DocArticleUuid="740BFF98FFCC957CCC54A30CFFD62C15" BibYear="2021" BibSource="European Journal of Taxonomy" BibVolume="746" BibIssue="0" BibFirstPage="98" BibLastPage="103" CitTreatCitCount="5" CitFigCitCount="1" CitTabCitCount="3"/>
<statData DocCount="1" DocUuid="03BD87E66B03FFA6AF89FAD8FD1E3979" DocDoi="http://doi.org/10.5281/zenodo.4534534" DocArticleUuid="FF84FF9E6B61FFC5AF1EF86AFFDE3D4C" BibYear="2021" BibSource="Zootaxa" BibVolume="4922" BibIssue="1" BibFirstPage="99" BibLastPage="100" CitTreatCitCount="6" CitFigCitCount="4" CitTabCitCount="1"/>
<statData DocCount="1" DocUuid="03BD87E66B02FFA0AF89FCECFCD139ED" DocDoi="http://doi.org/10.5281/zenodo.4534538" DocArticleUuid="FF84FF9E6B61FFC5AF1EF86AFFDE3D4C" BibYear="2021" BibSource="Zootaxa" BibVolume="4922" BibIssue="1" BibFirstPage="100" BibLastPage="102" CitTreatCitCount="6" CitFigCitCount="4" CitTabCitCount="1"/>
<statData DocCount="1" DocUuid="335587B2C4321C68FF28FAE7FAC5FC10" DocDoi="http://doi.org/10.5281/zenodo.4474413" DocArticleUuid="CF6CFFCAC4571C0EFFBFFA70FFE5FFD9" BibYear="2021" BibSource="Zootaxa" BibVolume="4918" BibIssue="1" BibFirstPage="102" BibLastPage="103" CitTreatCitCount="5" CitFigCitCount="4" CitTabCitCount="3"/>
<statData DocCount="1" DocUuid="039F879D027BFFDF57B3F88BFCF1769A" DocDoi="http://doi.org/10.5281/zenodo.4685423" DocArticleUuid="FFA6FFE5027AFFDD5724FF85FFD17577" BibYear="2021" BibSource="Zootaxa" BibVolume="4952" BibIssue="1" BibFirstPage="102" BibLastPage="103" CitTreatCitCount="6" CitFigCitCount="2" CitTabCitCount="1"/>
<statData DocCount="1" DocUuid="03BD87E66B04FFA2AF89FC98FD1E3C0D" DocDoi="http://doi.org/10.5281/zenodo.4534542" DocArticleUuid="FF84FF9E6B61FFC5AF1EF86AFFDE3D4C" BibYear="2021" BibSource="Zootaxa" BibVolume="4922" BibIssue="1" BibFirstPage="102" BibLastPage="104" CitTreatCitCount="4" CitFigCitCount="4" CitTabCitCount="1"/>
<statData DocCount="1" DocUuid="335587B2C4311C66FF28FE6AFA65FEC4" DocDoi="http://doi.org/10.5281/zenodo.4474415" DocArticleUuid="CF6CFFCAC4571C0EFFBFFA70FFE5FFD9" BibYear="2021" BibSource="Zootaxa" BibVolume="4918" BibIssue="1" BibFirstPage="103" BibLastPage="105" CitTreatCitCount="6" CitFigCitCount="3" CitTabCitCount="3"/>
<statData DocCount="1" DocUuid="039F879D0278FFD957B3FBBBFD9F776E" DocDoi="http://doi.org/10.5281/zenodo.4685425" DocArticleUuid="FFA6FFE5027AFFDD5724FF85FFD17577" BibYear="2021" BibSource="Zootaxa" BibVolume="4952" BibIssue="1" BibFirstPage="103" BibLastPage="105" CitTreatCitCount="7" CitFigCitCount="5" CitTabCitCount="1"/>
<statData DocCount="1" DocUuid="03F787DF1D01D970FE6A685784A6FB9B" DocDoi="http://doi.org/10.5281/zenodo.4615165" DocArticleUuid="FFCEFFA71D0DD960FF886D158538FF88" BibYear="2021" BibSource="European Journal of Taxonomy" BibVolume="739" BibIssue="1" BibFirstPage="104" BibLastPage="108" CitTreatCitCount="3" CitFigCitCount="18" CitTabCitCount="3"/>
<statData DocCount="1" DocUuid="039F879D027EFFD857B3FDEFFDFC767A" DocDoi="http://doi.org/10.5281/zenodo.4685427" DocArticleUuid="FFA6FFE5027AFFDD5724FF85FFD17577" BibYear="2021" BibSource="Zootaxa" BibVolume="4952" BibIssue="1" BibFirstPage="105" BibLastPage="106" CitTreatCitCount="2" CitFigCitCount="4" CitTabCitCount="1"/>
<statData DocCount="1" DocUuid="335587B2C43F1C64FF28FC67FAA7FD2B" DocDoi="http://doi.org/10.5281/zenodo.4474419" DocArticleUuid="CF6CFFCAC4571C0EFFBFFA70FFE5FFD9" BibYear="2021" BibSource="Zootaxa" BibVolume="4918" BibIssue="1" BibFirstPage="105" BibLastPage="107" CitTreatCitCount="8" CitFigCitCount="2" CitTabCitCount="3"/>
<statData DocCount="1" DocUuid="03BD87E66B09FFAFAF89FF64FD1E387D" DocDoi="http://doi.org/10.5281/zenodo.4560712" DocArticleUuid="FF84FF9E6B61FFC5AF1EF86AFFDE3D4C" BibYear="2021" BibSource="Zootaxa" BibVolume="4922" BibIssue="1" BibFirstPage="105" BibLastPage="107" CitTreatCitCount="2" CitFigCitCount="4" CitTabCitCount="1"/>
<statData DocCount="1" DocUuid="039F879D027FFFD857B3FCDAFB237209" DocDoi="http://doi.org/10.5281/zenodo.4685429" DocArticleUuid="FFA6FFE5027AFFDD5724FF85FFD17577" BibYear="2021" BibSource="Zootaxa" BibVolume="4952" BibIssue="1" BibFirstPage="106" BibLastPage="106" CitTreatCitCount="5" CitFigCitCount="5" CitTabCitCount="1"/>
<statData DocCount="1" DocUuid="03BD87E66B0BFFAEAF89FDE8FD1E3AF5" DocDoi="http://doi.org/10.5281/zenodo.4534550" DocArticleUuid="FF84FF9E6B61FFC5AF1EF86AFFDE3D4C" BibYear="2021" BibSource="Zootaxa" BibVolume="4922" BibIssue="1" BibFirstPage="107" BibLastPage="108" CitTreatCitCount="6" CitFigCitCount="4" CitTabCitCount="1"/>
<statData DocCount="1" DocUuid="335587B2C43D1C63FF28FD6AFB55FE98" DocDoi="http://doi.org/10.5281/zenodo.4474421" DocArticleUuid="CF6CFFCAC4571C0EFFBFFA70FFE5FFD9" BibYear="2021" BibSource="Zootaxa" BibVolume="4918" BibIssue="1" BibFirstPage="107" BibLastPage="110" CitTreatCitCount="1" CitFigCitCount="3" CitTabCitCount="3"/>
<statData DocCount="1" DocUuid="03B787E5BA42C122FDAF19537099044E" DocDoi="http://doi.org/10.5281/zenodo.4509042" DocArticleUuid="FF8EFF9DBA54C13AFFFD185B745C0538" BibYear="2021" BibSource="European Journal of Taxonomy" BibVolume="733" BibIssue="0" BibFirstPage="109" BibLastPage="111" CitTreatCitCount="11" CitFigCitCount="18" CitTabCitCount="1"/>
<statData DocCount="1" DocUuid="039F879D0272FFD557B3FF12FAA3714E" DocDoi="http://doi.org/10.5281/zenodo.4671814" DocArticleUuid="FFA6FFE5027AFFDD5724FF85FFD17577" BibYear="2021" BibSource="Zootaxa" BibVolume="4952" BibIssue="1" BibFirstPage="109" BibLastPage="109" CitTreatCitCount="7" CitFigCitCount="2" CitTabCitCount="1"/>
<statData DocCount="1" DocUuid="03A6D248FFF08B21DD7CFEA7FAB4D1D1" DocDoi="http://doi.org/10.5281/zenodo.4602483" DocArticleUuid="FF9FAA30FF9C8B52DF38FFAFFFC3D05C" BibYear="2021" BibSource="European Journal of Taxonomy" BibVolume="737" BibIssue="1" BibFirstPage="109" BibLastPage="115" CitTreatCitCount="7" CitFigCitCount="11" CitTabCitCount="2"/>
<statData DocCount="1" DocUuid="03BC87C5FFD63974A363FBBDFC72FDF1" DocDoi="http://doi.org/10.5281/zenodo.4767951" DocArticleUuid="FF85FFBDFFD23973A03CFFA9FFECFF81" BibYear="2021" BibSource="Adansonia" BibVolume="43" BibIssue="10" BibFirstPage="109" BibLastPage="112" CitTreatCitCount="3" CitFigCitCount="2" CitTabCitCount="1"/>
<statData DocCount="1" DocUuid="361087A7FFA8FFD355ABFE5B5349CEC2" DocDoi="http://doi.org/10.5281/zenodo.4473058" DocArticleUuid="CA29FFDFFFC5FFA0553CFFA5506ACD15" BibYear="2021" BibSource="Zootaxa" BibVolume="4912" BibIssue="1" BibFirstPage="110" BibLastPage="116" CitTreatCitCount="11" CitFigCitCount="29" CitTabCitCount="3"/>
<statData DocCount="1" DocUuid="03B787E5BA4CC120FE1619C776B604EF" DocDoi="http://doi.org/10.5281/zenodo.4509044" DocArticleUuid="FF8EFF9DBA54C13AFFFD185B745C0538" BibYear="2021" BibSource="European Journal of Taxonomy" BibVolume="733" BibIssue="0" BibFirstPage="111" BibLastPage="113" CitTreatCitCount="4" CitFigCitCount="16" CitTabCitCount="1"/>
<statData DocCount="1" DocUuid="039F879D0270FFD157B3FC2AFE6E7436" DocDoi="http://doi.org/10.5281/zenodo.4723841" DocArticleUuid="FFA6FFE5027AFFDD5724FF85FFD17577" BibYear="2021" BibSource="Zootaxa" BibVolume="4952" BibIssue="1" BibFirstPage="111" BibLastPage="113" CitTreatCitCount="3" CitFigCitCount="11" CitTabCitCount="1"/>
<statData DocCount="1" DocUuid="03B787E5BA4EC121FE1A1A5E70DB002C" DocDoi="http://doi.org/10.5281/zenodo.4509046" DocArticleUuid="FF8EFF9DBA54C13AFFFD185B745C0538" BibYear="2021" BibSource="European Journal of Taxonomy" BibVolume="733" BibIssue="0" BibFirstPage="113" BibLastPage="114" CitTreatCitCount="8" CitFigCitCount="16" CitTabCitCount="1"/>
<statData DocCount="1" DocUuid="039F879D0276FFD057B3FE17FC377469" DocDoi="http://doi.org/10.5281/zenodo.4685431" DocArticleUuid="FFA6FFE5027AFFDD5724FF85FFD17577" BibYear="2021" BibSource="Zootaxa" BibVolume="4952" BibIssue="1" BibFirstPage="113" BibLastPage="114" CitTreatCitCount="3" CitFigCitCount="16" CitTabCitCount="1"/>
<statData DocCount="1" DocUuid="03B63E6AE43BFFCEF7E91D94FCFEFC7E" DocDoi="http://doi.org/10.5281/zenodo.4664499" DocArticleUuid="FF8F4612E431FFC0F77E1B66FFD4FFDB" BibYear="2021" BibSource="Zootaxa" BibVolume="4950" BibIssue="1" BibFirstPage="113" BibLastPage="117" CitTreatCitCount="1" CitFigCitCount="7" CitTabCitCount="1"/>
<statData DocCount="1" DocUuid="03B787E5BA48C124FDD11C76763203AB" DocDoi="http://doi.org/10.5281/zenodo.4509060" DocArticleUuid="FF8EFF9DBA54C13AFFFD185B745C0538" BibYear="2021" BibSource="European Journal of Taxonomy" BibVolume="733" BibIssue="0" BibFirstPage="115" BibLastPage="117" CitTreatCitCount="1" CitFigCitCount="28" CitTabCitCount="1"/>
<statData DocCount="1" DocUuid="03A6D248FFEF8B2ADD59FE65FBC4D4D9" DocDoi="http://doi.org/10.5281/zenodo.4602485" DocArticleUuid="FF9FAA30FF9C8B52DF38FFAFFFC3D05C" BibYear="2021" BibSource="European Journal of Taxonomy" BibVolume="737" BibIssue="1" BibFirstPage="116" BibLastPage="121" CitTreatCitCount="3" CitFigCitCount="8" CitTabCitCount="2"/>
<statData DocCount="1" DocUuid="361087A7FFB6FFD855ABFADC5370C8F0" DocDoi="http://doi.org/10.5281/zenodo.4473064" DocArticleUuid="CA29FFDFFFC5FFA0553CFFA5506ACD15" BibYear="2021" BibSource="Zootaxa" BibVolume="4912" BibIssue="1" BibFirstPage="116" BibLastPage="121" CitTreatCitCount="6" CitFigCitCount="21" CitTabCitCount="2"/>
<statData DocCount="1" DocUuid="039F879D026AFFCC57B3FAAAFE6C7716" DocDoi="http://doi.org/10.5281/zenodo.4685433" DocArticleUuid="FFA6FFE5027AFFDD5724FF85FFD17577" BibYear="2021" BibSource="Zootaxa" BibVolume="4952" BibIssue="1" BibFirstPage="117" BibLastPage="118" CitTreatCitCount="5" CitFigCitCount="2" CitTabCitCount="1"/>
<statData DocCount="1" DocUuid="039F879D026BFFCC57B3FD37FBF072CA" DocDoi="http://doi.org/10.5281/zenodo.4685435" DocArticleUuid="FFA6FFE5027AFFDD5724FF85FFD17577" BibYear="2021" BibSource="Zootaxa" BibVolume="4952" BibIssue="1" BibFirstPage="118" BibLastPage="118" CitTreatCitCount="7" CitFigCitCount="6" CitTabCitCount="1"/>
<statData DocCount="1" DocUuid="039F879D0269FFC957B3FF12FF2176BF" DocDoi="http://doi.org/10.5281/zenodo.4685437" DocArticleUuid="FFA6FFE5027AFFDD5724FF85FFD17577" BibYear="2021" BibSource="Zootaxa" BibVolume="4952" BibIssue="1" BibFirstPage="120" BibLastPage="121" CitTreatCitCount="3" CitFigCitCount="2" CitTabCitCount="1"/>
<statData DocCount="1" DocUuid="03BD87E66B19FFBDAF89FB28FD1E3803" DocDoi="http://doi.org/10.5281/zenodo.4496532" DocArticleUuid="FF84FF9E6B61FFC5AF1EF86AFFDE3D4C" BibYear="2021" BibSource="Zootaxa" BibVolume="4922" BibIssue="1" BibFirstPage="121" BibLastPage="121" CitTreatCitCount="2" CitFigCitCount="2" CitTabCitCount="1"/>
<statData DocCount="1" DocUuid="03BD87E66B19FFBEAF89FD83FD1E3E59" DocDoi="http://doi.org/10.5281/zenodo.4560714" DocArticleUuid="FF84FF9E6B61FFC5AF1EF86AFFDE3D4C" BibYear="2021" BibSource="Zootaxa" BibVolume="4922" BibIssue="1" BibFirstPage="121" BibLastPage="124" CitTreatCitCount="4" CitFigCitCount="4" CitTabCitCount="1"/>
<statData DocCount="1" DocUuid="361087A7FFBCFF2055ABFF32515DC968" DocDoi="http://doi.org/10.5281/zenodo.4473068" DocArticleUuid="CA29FFDFFFC5FFA0553CFFA5506ACD15" BibYear="2021" BibSource="Zootaxa" BibVolume="4912" BibIssue="1" BibFirstPage="122" BibLastPage="129" CitTreatCitCount="31" CitFigCitCount="45" CitTabCitCount="3"/>
<statData DocCount="1" DocUuid="03BD87E66B1DFFBBAF89F977FD103E11" DocDoi="http://doi.org/10.5281/zenodo.4534569" DocArticleUuid="FF84FF9E6B61FFC5AF1EF86AFFDE3D4C" BibYear="2021" BibSource="Zootaxa" BibVolume="4922" BibIssue="1" BibFirstPage="125" BibLastPage="127" CitTreatCitCount="1" CitFigCitCount="3" CitTabCitCount="1"/>
<statData DocCount="1" DocUuid="03BD87E66B1EFF44AF89FEACFD103F2D" DocDoi="http://doi.org/10.5281/zenodo.4534573" DocArticleUuid="FF84FF9E6B61FFC5AF1EF86AFFDE3D4C" BibYear="2021" BibSource="Zootaxa" BibVolume="4922" BibIssue="1" BibFirstPage="128" BibLastPage="130" CitTreatCitCount="2" CitFigCitCount="4" CitTabCitCount="1"/>
<statData DocCount="1" DocUuid="03BD87E66BE6FF4DAF89FF05FD103ED4" DocDoi="http://doi.org/10.5281/zenodo.4537540" DocArticleUuid="FF84FF9E6B61FFC5AF1EF86AFFDE3D4C" BibYear="2021" BibSource="Zootaxa" BibVolume="4922" BibIssue="1" BibFirstPage="136" BibLastPage="137" CitTreatCitCount="6" CitFigCitCount="2" CitTabCitCount="1"/>
<statData DocCount="1" DocUuid="03BD87E66BE8FF4FAF89F977FD103FC9" DocDoi="http://doi.org/10.5281/zenodo.4560716" DocArticleUuid="FF84FF9E6B61FFC5AF1EF86AFFDE3D4C" BibYear="2021" BibSource="Zootaxa" BibVolume="4922" BibIssue="1" BibFirstPage="138" BibLastPage="139" CitTreatCitCount="5" CitFigCitCount="4" CitTabCitCount="1"/>
<statData DocCount="1" DocUuid="03BD87E66BEBFF49AF89FB29FD103835" DocDoi="http://doi.org/10.5281/zenodo.4534583" DocArticleUuid="FF84FF9E6B61FFC5AF1EF86AFFDE3D4C" BibYear="2021" BibSource="Zootaxa" BibVolume="4922" BibIssue="1" BibFirstPage="139" BibLastPage="141" CitTreatCitCount="3" CitFigCitCount="3" CitTabCitCount="1"/>
<statData DocCount="1" DocUuid="03D887EF620FFFA878DDFF016880F856" DocDoi="http://doi.org/10.5281/zenodo.4458059" DocArticleUuid="FFE1FF976209FFA2784AFF966A79FFAE" BibYear="2021" BibSource="Zootaxa" BibVolume="4915" BibIssue="1" BibFirstPage="139" BibLastPage="143" CitTreatCitCount="4" CitFigCitCount="6" CitTabCitCount="1"/>
<statData DocCount="1" DocUuid="03BD87E66BEDFF48AF89FDA0FD103BD5" DocDoi="http://doi.org/10.5281/zenodo.4534585" DocArticleUuid="FF84FF9E6B61FFC5AF1EF86AFFDE3D4C" BibYear="2021" BibSource="Zootaxa" BibVolume="4922" BibIssue="1" BibFirstPage="141" BibLastPage="142" CitTreatCitCount="1" CitFigCitCount="4" CitTabCitCount="1"/>
<statData DocCount="1" DocUuid="03BD87E66BECFF4BAF89FE80FD103AF5" DocDoi="http://doi.org/10.5281/zenodo.4496576" DocArticleUuid="FF84FF9E6B61FFC5AF1EF86AFFDE3D4C" BibYear="2021" BibSource="Zootaxa" BibVolume="4922" BibIssue="1" BibFirstPage="142" BibLastPage="143" CitTreatCitCount="3" CitFigCitCount="4" CitTabCitCount="1"/>
<statData DocCount="1" DocUuid="039287A73852FFC3FF4FFC4EFD668A98" DocDoi="http://doi.org/10.5281/zenodo.4422836" DocArticleUuid="FFABFFDF3850FFC5FFD8FF83FFC68F70" BibYear="2021" BibSource="Zootaxa" BibVolume="4903" BibIssue="1" BibFirstPage="142" BibLastPage="146" CitTreatCitCount="1" CitFigCitCount="35" CitTabCitCount="1"/>
<statData DocCount="1" DocUuid="03BD87E66BF5FF50AF89FE80FD103C0D" DocDoi="http://doi.org/10.5281/zenodo.4534597" DocArticleUuid="FF84FF9E6B61FFC5AF1EF86AFFDE3D4C" BibYear="2021" BibSource="Zootaxa" BibVolume="4922" BibIssue="1" BibFirstPage="149" BibLastPage="150" CitTreatCitCount="1" CitFigCitCount="2" CitTabCitCount="1"/>
<statData DocCount="1" DocUuid="03BD87E66BF6FF5DAF89F9B0FD103EE9" DocDoi="http://doi.org/10.5281/zenodo.4534599" DocArticleUuid="FF84FF9E6B61FFC5AF1EF86AFFDE3D4C" BibYear="2021" BibSource="Zootaxa" BibVolume="4922" BibIssue="1" BibFirstPage="152" BibLastPage="153" CitTreatCitCount="8" CitFigCitCount="4" CitTabCitCount="1"/>
<statData DocCount="1" DocUuid="A66B1A7CEF51D324FF0FFBB70945FCBF" DocDoi="http://doi.org/10.5281/zenodo.4651560" DocArticleUuid="5A526204EF53D322FF98FFAA0D6FFF86" BibYear="2021" BibSource="Zootaxa" BibVolume="4948" BibIssue="2" BibFirstPage="153" BibLastPage="157" CitTreatCitCount="40" CitFigCitCount="33" CitTabCitCount="12"/>
<statData DocCount="1" DocUuid="03BD87E66BF8FF5CAF89FE03FD103AB6" DocDoi="http://doi.org/10.5281/zenodo.4496606" DocArticleUuid="FF84FF9E6B61FFC5AF1EF86AFFDE3D4C" BibYear="2021" BibSource="Zootaxa" BibVolume="4922" BibIssue="1" BibFirstPage="154" BibLastPage="154" CitTreatCitCount="8" CitFigCitCount="2" CitTabCitCount="1"/>
<statData DocCount="1" DocUuid="03BD87E66BFAFF59AF89F8FDFD103D99" DocDoi="http://doi.org/10.5281/zenodo.4496612" DocArticleUuid="FF84FF9E6B61FFC5AF1EF86AFFDE3D4C" BibYear="2021" BibSource="Zootaxa" BibVolume="4922" BibIssue="1" BibFirstPage="156" BibLastPage="157" CitTreatCitCount="2" CitFigCitCount="4" CitTabCitCount="1"/>
<statData DocCount="1" DocUuid="03C787B8FFA7FFE3B55B56E6FD4BD7BE" DocDoi="http://doi.org/10.5281/zenodo.4694713" DocArticleUuid="FFFEFFC0FFACFFF2B708540DFFFED01B" BibYear="2021" BibSource="European Journal of Taxonomy" BibVolume="744" BibIssue="1" BibFirstPage="156" BibLastPage="162" CitTreatCitCount="1" CitFigCitCount="51" CitTabCitCount="1"/>
<statData DocCount="1" DocUuid="5B678789FFC11458A09D0CE9FB5FFAB4" DocDoi="http://doi.org/10.5281/zenodo.4564945" DocArticleUuid="A75EFFF1FFC4144AA00A0C7FFFCEFFE1" BibYear="2021" BibSource="Zootaxa" BibVolume="4927" BibIssue="2" BibFirstPage="156" BibLastPage="169" CitTreatCitCount="38" CitFigCitCount="19" CitTabCitCount="1"/>
<statData DocCount="1" DocUuid="D03F87E4D11D5054FF42DAF74890AE64" DocDoi="http://doi.org/10.5281/zenodo.4685801" DocArticleUuid="2C06FF9CD1185052FFD5DF594C5AAC59" BibYear="2021" BibSource="Zootaxa" BibVolume="4952" BibIssue="1" BibFirstPage="157" BibLastPage="157" CitTreatCitCount="1" CitFigCitCount="6" CitTabCitCount="1"/>
<statData DocCount="1" DocUuid="03BD87E66BFDFF58AF89F94CFB713DB6" DocDoi="http://doi.org/10.5281/zenodo.4496620" DocArticleUuid="FF84FF9E6B61FFC5AF1EF86AFFDE3D4C" BibYear="2021" BibSource="Zootaxa" BibVolume="4922" BibIssue="1" BibFirstPage="157" BibLastPage="158" CitTreatCitCount="4" CitFigCitCount="4" CitTabCitCount="1"/>
<statData DocCount="1" DocUuid="03BD87E66BFCFF5AAF89FF41FD103CE1" DocDoi="http://doi.org/10.5281/zenodo.4534607" DocArticleUuid="FF84FF9E6B61FFC5AF1EF86AFFDE3D4C" BibYear="2021" BibSource="Zootaxa" BibVolume="4922" BibIssue="1" BibFirstPage="158" BibLastPage="160" CitTreatCitCount="4" CitFigCitCount="4" CitTabCitCount="1"/>
<statData DocCount="1" DocUuid="03BF87A3C846FFBDFF3DFA7FFA28A2F6" DocDoi="http://doi.org/10.5281/zenodo.4559926" DocArticleUuid="FF86FFDBC841FFB7FFAAFFDEFFA5A577" BibYear="2021" BibSource="Zootaxa" BibVolume="4933" BibIssue="2" BibFirstPage="158" BibLastPage="161" CitTreatCitCount="9" CitFigCitCount="9" CitTabCitCount="1"/>
<statData DocCount="1" DocUuid="D03F87E4D11F505BFF42DAAC4DA5AD18" DocDoi="http://doi.org/10.5281/zenodo.4685811" DocArticleUuid="2C06FF9CD1185052FFD5DF594C5AAC59" BibYear="2021" BibSource="Zootaxa" BibVolume="4952" BibIssue="1" BibFirstPage="159" BibLastPage="162" CitTreatCitCount="1" CitFigCitCount="18" CitTabCitCount="3"/>
<statData DocCount="1" DocUuid="03BD87E66BC1FF64AF89FD05FD103BD5" DocDoi="http://doi.org/10.5281/zenodo.4496626" DocArticleUuid="FF84FF9E6B61FFC5AF1EF86AFFDE3D4C" BibYear="2021" BibSource="Zootaxa" BibVolume="4922" BibIssue="1" BibFirstPage="161" BibLastPage="162" CitTreatCitCount="3" CitFigCitCount="4" CitTabCitCount="1"/>
<statData DocCount="1" DocUuid="C24787C5BF59FFFCFF74F3CD6847633A" DocDoi="http://doi.org/10.5281/zenodo.4569769" DocArticleUuid="3E7EFFBDBF53FFF7FFE3F062697E627B" BibYear="2021" BibSource="Zootaxa" BibVolume="4903" BibIssue="2" BibFirstPage="161" BibLastPage="161" CitTreatCitCount="3" CitFigCitCount="4" CitTabCitCount="1"/>
<statData DocCount="1" DocUuid="C24787C5BF58FFFCFF74F1F16DFA66E0" DocDoi="http://doi.org/10.5281/zenodo.4569771" DocArticleUuid="3E7EFFBDBF53FFF7FFE3F062697E627B" BibYear="2021" BibSource="Zootaxa" BibVolume="4903" BibIssue="2" BibFirstPage="162" BibLastPage="162" CitTreatCitCount="1" CitFigCitCount="4" CitTabCitCount="1"/>
<statData DocCount="1" DocUuid="03BF87A3C84AFFBBFF3DFF49FE5BA167" DocDoi="http://doi.org/10.5281/zenodo.4559928" DocArticleUuid="FF86FFDBC841FFB7FFAAFFDEFFA5A577" BibYear="2021" BibSource="Zootaxa" BibVolume="4933" BibIssue="2" BibFirstPage="162" BibLastPage="163" CitTreatCitCount="1" CitFigCitCount="4" CitTabCitCount="1"/>
<statData DocCount="1" DocUuid="D03F87E4D113505EFF42DFCE4DF1AD18" DocDoi="http://doi.org/10.5281/zenodo.4685815" DocArticleUuid="2C06FF9CD1185052FFD5DF594C5AAC59" BibYear="2021" BibSource="Zootaxa" BibVolume="4952" BibIssue="1" BibFirstPage="163" BibLastPage="164" CitTreatCitCount="1" CitFigCitCount="1" CitTabCitCount="1"/>
<statData DocCount="1" DocUuid="03C787B8FFBEFFE4B5695504FBA0D247" DocDoi="http://doi.org/10.5281/zenodo.4694715" DocArticleUuid="FFFEFFC0FFACFFF2B708540DFFFED01B" BibYear="2021" BibSource="European Journal of Taxonomy" BibVolume="744" BibIssue="1" BibFirstPage="163" BibLastPage="167" CitTreatCitCount="8" CitFigCitCount="27" CitTabCitCount="1"/>
<statData DocCount="1" DocUuid="C24787C5BF5FFFFBFF74F417685B64C1" DocDoi="http://doi.org/10.5281/zenodo.4422923" DocArticleUuid="3E7EFFBDBF53FFF7FFE3F062697E627B" BibYear="2021" BibSource="Zootaxa" BibVolume="4903" BibIssue="2" BibFirstPage="163" BibLastPage="163" CitTreatCitCount="1" CitFigCitCount="4" CitTabCitCount="1"/>
<statData DocCount="1" DocUuid="C24787C5BF5FFFFBFF74F11968E36653" DocDoi="http://doi.org/10.5281/zenodo.4569781" DocArticleUuid="3E7EFFBDBF53FFF7FFE3F062697E627B" BibYear="2021" BibSource="Zootaxa" BibVolume="4903" BibIssue="2" BibFirstPage="163" BibLastPage="163" CitTreatCitCount="2" CitFigCitCount="5" CitTabCitCount="1"/>
<statData DocCount="1" DocUuid="03E587FAFFABFFAEFF2A5B052E7F7733" DocDoi="http://doi.org/10.5281/zenodo.4534246" DocArticleUuid="FFDCFF82FFA7FFA0FFBD5F132D13762E" BibYear="2021" BibSource="Zootaxa" BibVolume="4926" BibIssue="2" BibFirstPage="163" BibLastPage="164" CitTreatCitCount="5" CitFigCitCount="22" CitTabCitCount="1"/>
<statData DocCount="1" DocUuid="D03F87E4D114505EFF42DECA480EAF0E" DocDoi="http://doi.org/10.5281/zenodo.4685819" DocArticleUuid="2C06FF9CD1185052FFD5DF594C5AAC59" BibYear="2021" BibSource="Zootaxa" BibVolume="4952" BibIssue="1" BibFirstPage="164" BibLastPage="164" CitTreatCitCount="1" CitFigCitCount="1" CitTabCitCount="1"/>
<statData DocCount="1" DocUuid="03BF87A3C84FFFA7FF3DFCCFFE0FA436" DocDoi="http://doi.org/10.5281/zenodo.4559930" DocArticleUuid="FF86FFDBC841FFB7FFAAFFDEFFA5A577" BibYear="2021" BibSource="Zootaxa" BibVolume="4933" BibIssue="2" BibFirstPage="165" BibLastPage="167" CitTreatCitCount="5" CitFigCitCount="4" CitTabCitCount="1"/>
<statData DocCount="1" DocUuid="03C787B8FFBAFFEFB6F55694FB4BD172" DocDoi="http://doi.org/10.5281/zenodo.4694719" DocArticleUuid="FFFEFFC0FFACFFF2B708540DFFFED01B" BibYear="2021" BibSource="European Journal of Taxonomy" BibVolume="744" BibIssue="1" BibFirstPage="167" BibLastPage="173" CitTreatCitCount="3" CitFigCitCount="24" CitTabCitCount="1"/>
<statData DocCount="1" DocUuid="0386CD35FF9BFFA77458FC6A400B90BE" DocDoi="http://doi.org/10.5281/zenodo.4721075" DocArticleUuid="FFBFB54DFF9CFFA0757CFF9F44099755" BibYear="2021" BibSource="Zoosystema" BibVolume="43" BibIssue="10" BibFirstPage="168" BibLastPage="168" CitTreatCitCount="8" CitFigCitCount="1" CitTabCitCount="1"/>
<statData DocCount="1" DocUuid="03BF87A3C853FFA3FF3DF9F4FE29A20A" DocDoi="http://doi.org/10.5281/zenodo.4559936" DocArticleUuid="FF86FFDBC841FFB7FFAAFFDEFFA5A577" BibYear="2021" BibSource="Zootaxa" BibVolume="4933" BibIssue="2" BibFirstPage="169" BibLastPage="171" CitTreatCitCount="1" CitFigCitCount="6" CitTabCitCount="1"/>
<statData DocCount="1" DocUuid="03E587FAFFB5FFB5FF2A5E592FD771BB" DocDoi="http://doi.org/10.5281/zenodo.4534254" DocArticleUuid="FFDCFF82FFA7FFA0FFBD5F132D13762E" BibYear="2021" BibSource="Zootaxa" BibVolume="4926" BibIssue="2" BibFirstPage="169" BibLastPage="172" CitTreatCitCount="2" CitFigCitCount="13" CitTabCitCount="1"/>
<statData DocCount="1" DocUuid="5B678789FFD61450A09D09D9FB9BFB08" DocDoi="http://doi.org/10.5281/zenodo.4564951" DocArticleUuid="A75EFFF1FFC4144AA00A0C7FFFCEFFE1" BibYear="2021" BibSource="Zootaxa" BibVolume="4927" BibIssue="2" BibFirstPage="169" BibLastPage="177" CitTreatCitCount="19" CitFigCitCount="22" CitTabCitCount="2"/>
<statData DocCount="1" DocUuid="C24787C5BF47FFE3FF74F0F56A6B61E0" DocDoi="http://doi.org/10.5281/zenodo.4422968" DocArticleUuid="3E7EFFBDBF53FFF7FFE3F062697E627B" BibYear="2021" BibSource="Zootaxa" BibVolume="4903" BibIssue="2" BibFirstPage="171" BibLastPage="171" CitTreatCitCount="1" CitFigCitCount="3" CitTabCitCount="1"/>
<statData DocCount="1" DocUuid="C24787C5BF47FFE3FF74F5F36BAC659D" DocDoi="http://doi.org/10.5281/zenodo.4422972" DocArticleUuid="3E7EFFBDBF53FFF7FFE3F062697E627B" BibYear="2021" BibSource="Zootaxa" BibVolume="4903" BibIssue="2" BibFirstPage="171" BibLastPage="171" CitTreatCitCount="1" CitFigCitCount="4" CitTabCitCount="1"/>
<statData DocCount="1" DocUuid="03BF87A3C854FFA0FF3DFF49FDC3A58E" DocDoi="http://doi.org/10.5281/zenodo.4559940" DocArticleUuid="FF86FFDBC841FFB7FFAAFFDEFFA5A577" BibYear="2021" BibSource="Zootaxa" BibVolume="4933" BibIssue="2" BibFirstPage="172" BibLastPage="174" CitTreatCitCount="7" CitFigCitCount="6" CitTabCitCount="1"/>
<statData DocCount="1" DocUuid="03BD87E66BCDFF69AF89FD5CFB9D3BBD" DocDoi="http://doi.org/10.5281/zenodo.4496650" DocArticleUuid="FF84FF9E6B61FFC5AF1EF86AFFDE3D4C" BibYear="2021" BibSource="Zootaxa" BibVolume="4922" BibIssue="1" BibFirstPage="173" BibLastPage="173" CitTreatCitCount="5" CitFigCitCount="2" CitTabCitCount="1"/>
<statData DocCount="1" DocUuid="03BF87A3C856FFA0FF3DFE94FC24A01E" DocDoi="http://doi.org/10.5281/zenodo.4550170" DocArticleUuid="FF86FFDBC841FFB7FFAAFFDEFFA5A577" BibYear="2021" BibSource="Zootaxa" BibVolume="4933" BibIssue="2" BibFirstPage="174" BibLastPage="174" CitTreatCitCount="3" CitFigCitCount="7" CitTabCitCount="1"/>
<statData DocCount="1" DocUuid="03BF87A3C856FFACFF3DFA64FECBA58E" DocDoi="http://doi.org/10.5281/zenodo.4559944" DocArticleUuid="FF86FFDBC841FFB7FFAAFFDEFFA5A577" BibYear="2021" BibSource="Zootaxa" BibVolume="4933" BibIssue="2" BibFirstPage="174" BibLastPage="177" CitTreatCitCount="11" CitFigCitCount="3" CitTabCitCount="1"/>
<statData DocCount="1" DocUuid="361087A7FF75FF1755ABFA485204CFE4" DocDoi="http://doi.org/10.5281/zenodo.4473114" DocArticleUuid="CA29FFDFFFC5FFA0553CFFA5506ACD15" BibYear="2021" BibSource="Zootaxa" BibVolume="4912" BibIssue="1" BibFirstPage="177" BibLastPage="184" CitTreatCitCount="28" CitFigCitCount="24" CitTabCitCount="2"/>
<statData DocCount="1" DocUuid="03BF87A3C85AFFACFF3DFE94FCEAA1E6" DocDoi="http://doi.org/10.5281/zenodo.4559946" DocArticleUuid="FF86FFDBC841FFB7FFAAFFDEFFA5A577" BibYear="2021" BibSource="Zootaxa" BibVolume="4933" BibIssue="2" BibFirstPage="178" BibLastPage="178" CitTreatCitCount="1" CitFigCitCount="3" CitTabCitCount="1"/>
<statData DocCount="1" DocUuid="03BF87A3C85AFFACFF3DFB3CFDE6A282" DocDoi="http://doi.org/10.5281/zenodo.4559948" DocArticleUuid="FF86FFDBC841FFB7FFAAFFDEFFA5A577" BibYear="2021" BibSource="Zootaxa" BibVolume="4933" BibIssue="2" BibFirstPage="178" BibLastPage="178" CitTreatCitCount="4" CitFigCitCount="1" CitTabCitCount="1"/>
<statData DocCount="1" DocUuid="03BF87A3C85DFFAAFF3DFC19FE2AA4DA" DocDoi="http://doi.org/10.5281/zenodo.4559950" DocArticleUuid="FF86FFDBC841FFB7FFAAFFDEFFA5A577" BibYear="2021" BibSource="Zootaxa" BibVolume="4933" BibIssue="2" BibFirstPage="179" BibLastPage="180" CitTreatCitCount="8" CitFigCitCount="6" CitTabCitCount="1"/>
<statData DocCount="1" DocUuid="03BF87A3C85CFFA9FF3DFD43FB22A6D2" DocDoi="http://doi.org/10.5281/zenodo.4550184" DocArticleUuid="FF86FFDBC841FFB7FFAAFFDEFFA5A577" BibYear="2021" BibSource="Zootaxa" BibVolume="4933" BibIssue="2" BibFirstPage="180" BibLastPage="181" CitTreatCitCount="2" CitFigCitCount="5" CitTabCitCount="1"/>
<statData DocCount="1" DocUuid="03E587FAFFB9FF80FF2A5A462F857137" DocDoi="http://doi.org/10.5281/zenodo.4534260" DocArticleUuid="FFDCFF82FFA7FFA0FFBD5F132D13762E" BibYear="2021" BibSource="Zootaxa" BibVolume="4926" BibIssue="2" BibFirstPage="181" BibLastPage="183" CitTreatCitCount="2" CitFigCitCount="9" CitTabCitCount="1"/>
<statData DocCount="1" DocUuid="03BF87A3C85FFF96FF3DFC28FEB3A7BA" DocDoi="http://doi.org/10.5281/zenodo.4559954" DocArticleUuid="FF86FFDBC841FFB7FFAAFFDEFFA5A577" BibYear="2021" BibSource="Zootaxa" BibVolume="4933" BibIssue="2" BibFirstPage="181" BibLastPage="184" CitTreatCitCount="10" CitFigCitCount="10" CitTabCitCount="1"/>
<statData DocCount="1" DocUuid="03BF87A3C860FF95FF3DFAC8FE24A58F" DocDoi="http://doi.org/10.5281/zenodo.4550194" DocArticleUuid="FF86FFDBC841FFB7FFAAFFDEFFA5A577" BibYear="2021" BibSource="Zootaxa" BibVolume="4933" BibIssue="2" BibFirstPage="184" BibLastPage="185" CitTreatCitCount="2" CitFigCitCount="1" CitTabCitCount="1"/>
<statData DocCount="1" DocUuid="03D66E0179764E7E28F5FB35FE93F8D8" DocDoi="http://doi.org/10.5281/zenodo.4671584" DocArticleUuid="FFEF167979724E782862FFC7FFA6FFDB" BibYear="2021" BibSource="Zootaxa" BibVolume="4952" BibIssue="1" BibFirstPage="185" BibLastPage="187" CitTreatCitCount="5" CitFigCitCount="13" CitTabCitCount="2"/>
<statData DocCount="1" DocUuid="03BF87A3C863FF94FF3DFEE1FD72A482" DocDoi="http://doi.org/10.5281/zenodo.4559956" DocArticleUuid="FF86FFDBC841FFB7FFAAFFDEFFA5A577" BibYear="2021" BibSource="Zootaxa" BibVolume="4933" BibIssue="2" BibFirstPage="185" BibLastPage="186" CitTreatCitCount="3" CitFigCitCount="2" CitTabCitCount="1"/>
<statData DocCount="1" DocUuid="03BF87A3C862FF94FF3DFC32FDFDA3D4" DocDoi="http://doi.org/10.5281/zenodo.4559959" DocArticleUuid="FF86FFDBC841FFB7FFAAFFDEFFA5A577" BibYear="2021" BibSource="Zootaxa" BibVolume="4933" BibIssue="2" BibFirstPage="186" BibLastPage="186" CitTreatCitCount="3" CitFigCitCount="1" CitTabCitCount="1"/>
<statData DocCount="1" DocUuid="03BF87A3C862FF93FF3DF92AFB38A4A6" DocDoi="http://doi.org/10.5281/zenodo.4559961" DocArticleUuid="FF86FFDBC841FFB7FFAAFFDEFFA5A577" BibYear="2021" BibSource="Zootaxa" BibVolume="4933" BibIssue="2" BibFirstPage="186" BibLastPage="187" CitTreatCitCount="1" CitFigCitCount="1" CitTabCitCount="1"/>
<statData DocCount="1" DocUuid="03D66E0179744E7028F5F893FE5BF804" DocDoi="http://doi.org/10.5281/zenodo.4671588" DocArticleUuid="FFEF167979724E782862FFC7FFA6FFDB" BibYear="2021" BibSource="Zootaxa" BibVolume="4952" BibIssue="1" BibFirstPage="187" BibLastPage="189" CitTreatCitCount="4" CitFigCitCount="8" CitTabCitCount="1"/>
<statData DocCount="1" DocUuid="03BD87E66BDAFF7EAF89F999FD103FB3" DocDoi="http://doi.org/10.5281/zenodo.4537544" DocArticleUuid="FF84FF9E6B61FFC5AF1EF86AFFDE3D4C" BibYear="2021" BibSource="Zootaxa" BibVolume="4922" BibIssue="1" BibFirstPage="188" BibLastPage="188" CitTreatCitCount="4" CitFigCitCount="2" CitTabCitCount="1"/>
<statData DocCount="1" DocUuid="03BD87E66BDAFF78AF89FCF9FD133BF1" DocDoi="http://doi.org/10.5281/zenodo.4534666" DocArticleUuid="FF84FF9E6B61FFC5AF1EF86AFFDE3D4C" BibYear="2021" BibSource="Zootaxa" BibVolume="4922" BibIssue="1" BibFirstPage="188" BibLastPage="190" CitTreatCitCount="5" CitFigCitCount="4" CitTabCitCount="1"/>
<statData DocCount="1" DocUuid="03BD87E66BDCFF7AAF89FF69FD133C29" DocDoi="http://doi.org/10.5281/zenodo.4537546" DocArticleUuid="FF84FF9E6B61FFC5AF1EF86AFFDE3D4C" BibYear="2021" BibSource="Zootaxa" BibVolume="4922" BibIssue="1" BibFirstPage="190" BibLastPage="192" CitTreatCitCount="7" CitFigCitCount="4" CitTabCitCount="1"/>
<statData DocCount="1" DocUuid="03007E45FF82FF803D89FCF9F2F9B998" DocDoi="http://doi.org/10.5281/zenodo.4579397" DocArticleUuid="FF39063DFF81FF863D1EFF9FF35CBE7B" BibYear="2021" BibSource="Zootaxa" BibVolume="4938" BibIssue="2" BibFirstPage="199" BibLastPage="202" CitTreatCitCount="7" CitFigCitCount="14" CitTabCitCount="2"/>
<statData DocCount="1" DocUuid="03BD87E66BAEFF15AF89FB28FD133979" DocDoi="http://doi.org/10.5281/zenodo.4534697" DocArticleUuid="FF84FF9E6B61FFC5AF1EF86AFFDE3D4C" BibYear="2021" BibSource="Zootaxa" BibVolume="4922" BibIssue="1" BibFirstPage="208" BibLastPage="209" CitTreatCitCount="4" CitFigCitCount="4" CitTabCitCount="1"/>
<statData DocCount="1" DocUuid="03BD87E66BB3FF11AF89FD20FD133DFD" DocDoi="http://doi.org/10.5281/zenodo.4537553" DocArticleUuid="FF84FF9E6B61FFC5AF1EF86AFFDE3D4C" BibYear="2021" BibSource="Zootaxa" BibVolume="4922" BibIssue="1" BibFirstPage="211" BibLastPage="213" CitTreatCitCount="10" CitFigCitCount="4" CitTabCitCount="1"/>
<statData DocCount="1" DocUuid="E83387BFFFA5FF865094B705FBFC1D76" DocDoi="http://doi.org/10.5281/zenodo.4565566" DocArticleUuid="140AFFC7FFA6FF805003B276FFCA1F17" BibYear="2021" BibSource="Zootaxa" BibVolume="4927" BibIssue="2" BibFirstPage="212" BibLastPage="215" CitTreatCitCount="7" CitFigCitCount="3" CitTabCitCount="1"/>
<statData DocCount="1" DocUuid="03BD87E66BB4FF12AF89FBE8FD133E85" DocDoi="http://doi.org/10.5281/zenodo.4534709" DocArticleUuid="FF84FF9E6B61FFC5AF1EF86AFFDE3D4C" BibYear="2021" BibSource="Zootaxa" BibVolume="4922" BibIssue="1" BibFirstPage="214" BibLastPage="216" CitTreatCitCount="3" CitFigCitCount="4" CitTabCitCount="1"/>
<statData DocCount="1" DocUuid="03BD87E66BBCFF1AAF89FD9CFD133931" DocDoi="http://doi.org/10.5281/zenodo.4534736" DocArticleUuid="FF84FF9E6B61FFC5AF1EF86AFFDE3D4C" BibYear="2021" BibSource="Zootaxa" BibVolume="4922" BibIssue="1" BibFirstPage="222" BibLastPage="224" CitTreatCitCount="3" CitFigCitCount="4" CitTabCitCount="1"/>
<statData DocCount="1" DocUuid="03E287EBFFF1FFF0CAB14BF0FC13FE79" DocDoi="http://doi.org/10.5281/zenodo.4694847" DocArticleUuid="FFDBFF93FFF6FFFDCA264B67FF99FFA8" BibYear="2021" BibSource="Zootaxa" BibVolume="4952" BibIssue="2" BibFirstPage="242" BibLastPage="248" CitTreatCitCount="3" CitFigCitCount="24" CitTabCitCount="4"/>
<statData DocCount="1" DocUuid="6426795AFFD0905FFF5DEC5CFB50C9E3" DocDoi="http://doi.org/10.5281/zenodo.4749933" DocArticleUuid="981F0122FFD79052FFCAE865FFDEC862" BibYear="2021" BibSource="Zootaxa" BibVolume="4965" BibIssue="2" BibFirstPage="251" BibLastPage="257" CitTreatCitCount="1" CitFigCitCount="15" CitTabCitCount="2"/>
<statData DocCount="1" DocUuid="039CAA64605AFFD1FF633A7CD796FC96" DocDoi="http://doi.org/10.5281/zenodo.4582294" DocArticleUuid="FFA5D21C6059FFD7FFF43E5ED642FFAC" BibYear="2021" BibSource="Zootaxa" BibVolume="4938" BibIssue="3" BibFirstPage="254" BibLastPage="257" CitTreatCitCount="3" CitFigCitCount="8" CitTabCitCount="2"/>
<statData DocCount="1" DocUuid="9D767B515A0BFFC3C0F7919FF301FC8D" DocDoi="http://doi.org/10.5281/zenodo.4621213" DocArticleUuid="614F03295A09FFCBC0609214F156FFD3" BibYear="2021" BibSource="Zootaxa" BibVolume="4948" BibIssue="2" BibFirstPage="263" BibLastPage="268" CitTreatCitCount="11" CitFigCitCount="8" CitTabCitCount="3"/>
<statData DocCount="1" DocUuid="03BD87E66A6BFECEAF89FEC8FD1038D1" DocDoi="http://doi.org/10.5281/zenodo.4534821" DocArticleUuid="FF84FF9E6B61FFC5AF1EF86AFFDE3D4C" BibYear="2021" BibSource="Zootaxa" BibVolume="4922" BibIssue="1" BibFirstPage="267" BibLastPage="268" CitTreatCitCount="4" CitFigCitCount="3" CitTabCitCount="1"/>
<statData DocCount="1" DocUuid="039CAA64604AFFC2FF633EC9D534FB45" DocDoi="http://doi.org/10.5281/zenodo.4582304" DocArticleUuid="FFA5D21C6059FFD7FFF43E5ED642FFAC" BibYear="2021" BibSource="Zootaxa" BibVolume="4938" BibIssue="3" BibFirstPage="270" BibLastPage="272" CitTreatCitCount="2" CitFigCitCount="6" CitTabCitCount="1"/>
<statData DocCount="1" DocUuid="03BD87E66A6EFED4AF89FC08FD103EE9" DocDoi="http://doi.org/10.5281/zenodo.4534827" DocArticleUuid="FF84FF9E6B61FFC5AF1EF86AFFDE3D4C" BibYear="2021" BibSource="Zootaxa" BibVolume="4922" BibIssue="1" BibFirstPage="272" BibLastPage="274" CitTreatCitCount="3" CitFigCitCount="4" CitTabCitCount="1"/>
<statData DocCount="1" DocUuid="039CAA646042FFCBFF633A60D241FCB9" DocDoi="http://doi.org/10.5281/zenodo.4582314" DocArticleUuid="FFA5D21C6059FFD7FFF43E5ED642FFAC" BibYear="2021" BibSource="Zootaxa" BibVolume="4938" BibIssue="3" BibFirstPage="278" BibLastPage="279" CitTreatCitCount="2" CitFigCitCount="9" CitTabCitCount="2"/>
<statData DocCount="1" DocUuid="039CAA64607FFFFDFF633CA4D24AFE59" DocDoi="http://doi.org/10.5281/zenodo.4582323" DocArticleUuid="FFA5D21C6059FFD7FFF43E5ED642FFAC" BibYear="2021" BibSource="Zootaxa" BibVolume="4938" BibIssue="3" BibFirstPage="289" BibLastPage="293" CitTreatCitCount="3" CitFigCitCount="10" CitTabCitCount="2"/>
<statData DocCount="1" DocUuid="03DBDB11C177FFBDFF54FB48FA0FB2D5" DocDoi="http://doi.org/10.5281/zenodo.4710356" DocArticleUuid="FFE2A369C174FFBBFFC3FFE3FF93B443" BibYear="2021" BibSource="Zootaxa" BibVolume="4958" BibIssue="1" BibFirstPage="290" BibLastPage="293" CitTreatCitCount="4" CitFigCitCount="24" CitTabCitCount="3"/>
<statData DocCount="1" DocUuid="45376A353254B04CFF7CFD81234FF84E" DocDoi="http://doi.org/10.5281/zenodo.4545870" DocArticleUuid="B90E124D3257B041FFEBFFC62223FF9D" BibYear="2021" BibSource="Zootaxa" BibVolume="4926" BibIssue="3" BibFirstPage="304" BibLastPage="314" CitTreatCitCount="10" CitFigCitCount="8" CitTabCitCount="2"/>
<statData DocCount="1" DocUuid="03BD87E66A56FEFFAF89F9AFFD103CE1" DocDoi="http://doi.org/10.5281/zenodo.4537839" DocArticleUuid="FF84FF9E6B61FFC5AF1EF86AFFDE3D4C" BibYear="2021" BibSource="Zootaxa" BibVolume="4922" BibIssue="1" BibFirstPage="312" BibLastPage="315" CitTreatCitCount="5" CitFigCitCount="3" CitTabCitCount="1"/>
<statData DocCount="1" DocUuid="45376A353259B054FF7CFEE121FBFE4F" DocDoi="http://doi.org/10.5281/zenodo.4545874" DocArticleUuid="B90E124D3257B041FFEBFFC62223FF9D" BibYear="2021" BibSource="Zootaxa" BibVolume="4926" BibIssue="3" BibFirstPage="315" BibLastPage="322" CitTreatCitCount="46" CitFigCitCount="2" CitTabCitCount="1"/>
<statData DocCount="1" DocUuid="03BD87E66A5AFEF8AF89FB28FD103E11" DocDoi="http://doi.org/10.5281/zenodo.4534914" DocArticleUuid="FF84FF9E6B61FFC5AF1EF86AFFDE3D4C" BibYear="2021" BibSource="Zootaxa" BibVolume="4922" BibIssue="1" BibFirstPage="316" BibLastPage="318" CitTreatCitCount="5" CitFigCitCount="4" CitTabCitCount="1"/>
<statData DocCount="1" DocUuid="03BD87E66A5CFEFBAF89FC7AFD103E11" DocDoi="http://doi.org/10.5281/zenodo.4534930" DocArticleUuid="FF84FF9E6B61FFC5AF1EF86AFFDE3D4C" BibYear="2021" BibSource="Zootaxa" BibVolume="4922" BibIssue="1" BibFirstPage="318" BibLastPage="319" CitTreatCitCount="3" CitFigCitCount="3" CitTabCitCount="1"/>
<statData DocCount="1" DocUuid="03DB87830E45FF8FFF6B633FEB7D74BF" DocDoi="http://doi.org/10.5281/zenodo.4619200" DocArticleUuid="FFE2FFFB0E54FF9CFFFC6218E9117445" BibYear="2021" BibSource="Zootaxa" BibVolume="4942" BibIssue="3" BibFirstPage="318" BibLastPage="320" CitTreatCitCount="5" CitFigCitCount="4" CitTabCitCount="4"/>
<statData DocCount="1" DocUuid="03BD87E66A5FFEFAAF89FBC4FD58393B" DocDoi="http://doi.org/10.5281/zenodo.4534936" DocArticleUuid="FF84FF9E6B61FFC5AF1EF86AFFDE3D4C" BibYear="2021" BibSource="Zootaxa" BibVolume="4922" BibIssue="1" BibFirstPage="319" BibLastPage="320" CitTreatCitCount="6" CitFigCitCount="4" CitTabCitCount="1"/>
<statData DocCount="1" DocUuid="03DB87830E40FF8AFF6B670CEB0B7718" DocDoi="http://doi.org/10.5281/zenodo.4619202" DocArticleUuid="FFE2FFFB0E54FF9CFFFC6218E9117445" BibYear="2021" BibSource="Zootaxa" BibVolume="4942" BibIssue="3" BibFirstPage="321" BibLastPage="323" CitTreatCitCount="6" CitFigCitCount="3" CitTabCitCount="4"/>
<statData DocCount="1" DocUuid="03DB87830E42FF8BFF6B6746EC5D73D3" DocDoi="http://doi.org/10.5281/zenodo.4619204" DocArticleUuid="FFE2FFFB0E54FF9CFFFC6218E9117445" BibYear="2021" BibSource="Zootaxa" BibVolume="4942" BibIssue="3" BibFirstPage="323" BibLastPage="324" CitTreatCitCount="4" CitFigCitCount="3" CitTabCitCount="4"/>
<statData DocCount="1" DocUuid="03BD87E66A22FE80AF89FD7CFD103E75" DocDoi="http://doi.org/10.5281/zenodo.4560718" DocArticleUuid="FF84FF9E6B61FFC5AF1EF86AFFDE3D4C" BibYear="2021" BibSource="Zootaxa" BibVolume="4922" BibIssue="1" BibFirstPage="324" BibLastPage="326" CitTreatCitCount="5" CitFigCitCount="4" CitTabCitCount="1"/>
<statData DocCount="1" DocUuid="03DB87830E4CFF85FF6B6081ED737110" DocDoi="http://doi.org/10.5281/zenodo.4619208" DocArticleUuid="FFE2FFFB0E54FF9CFFFC6218E9117445" BibYear="2021" BibSource="Zootaxa" BibVolume="4942" BibIssue="3" BibFirstPage="325" BibLastPage="326" CitTreatCitCount="3" CitFigCitCount="3" CitTabCitCount="4"/>
<statData DocCount="1" DocUuid="03BD87E66A24FE83AF89FBE0FD103979" DocDoi="http://doi.org/10.5281/zenodo.4534944" DocArticleUuid="FF84FF9E6B61FFC5AF1EF86AFFDE3D4C" BibYear="2021" BibSource="Zootaxa" BibVolume="4922" BibIssue="1" BibFirstPage="326" BibLastPage="327" CitTreatCitCount="1" CitFigCitCount="4" CitTabCitCount="1"/>
<statData DocCount="1" DocUuid="03BD87E66A26FE8CAF89FD34FD103E59" DocDoi="http://doi.org/10.5281/zenodo.4534948" DocArticleUuid="FF84FF9E6B61FFC5AF1EF86AFFDE3D4C" BibYear="2021" BibSource="Zootaxa" BibVolume="4922" BibIssue="1" BibFirstPage="328" BibLastPage="330" CitTreatCitCount="6" CitFigCitCount="4" CitTabCitCount="1"/>
<statData DocCount="1" DocUuid="03BD87E66A2CFE8AAF89FBC4FD103915" DocDoi="http://doi.org/10.5281/zenodo.4534979" DocArticleUuid="FF84FF9E6B61FFC5AF1EF86AFFDE3D4C" BibYear="2021" BibSource="Zootaxa" BibVolume="4922" BibIssue="1" BibFirstPage="334" BibLastPage="336" CitTreatCitCount="1" CitFigCitCount="4" CitTabCitCount="1"/>
<statData DocCount="1" DocUuid="03BD87E66A2EFE95AF89FCC0FD103835" DocDoi="http://doi.org/10.5281/zenodo.4560720" DocArticleUuid="FF84FF9E6B61FFC5AF1EF86AFFDE3D4C" BibYear="2021" BibSource="Zootaxa" BibVolume="4922" BibIssue="1" BibFirstPage="336" BibLastPage="337" CitTreatCitCount="1" CitFigCitCount="4" CitTabCitCount="1"/>
<statData DocCount="1" DocUuid="03C67812FFDD9562FF1BFE36FEABFEF1" DocDoi="http://doi.org/10.5281/zenodo.4692074" DocArticleUuid="FFFF006AFFDF9565FF8CFF80FF86FFB3" BibYear="2021" BibSource="Zootaxa" BibVolume="4958" BibIssue="1" BibFirstPage="347" BibLastPage="352" CitTreatCitCount="11" CitFigCitCount="35" CitTabCitCount="1"/>
<statData DocCount="1" DocUuid="754287FAFFF2492BBA9224400E5EFE21" DocDoi="http://doi.org/10.5281/zenodo.4450584" DocArticleUuid="897BFF82FFF34922BA0521510D67FFAB" BibYear="2021" BibSource="Zootaxa" BibVolume="4908" BibIssue="3" BibFirstPage="355" BibLastPage="363" CitTreatCitCount="26" CitFigCitCount="13" CitTabCitCount="2"/>
<statData DocCount="1" DocUuid="03826F0FFFC4E075FF2BD5E30431FADA" DocDoi="http://doi.org/10.5281/zenodo.4683534" DocArticleUuid="FFBB1777FFC3E07DFFBCD7340108FFE8" BibYear="2021" BibSource="Zootaxa" BibVolume="4951" BibIssue="2" BibFirstPage="368" BibLastPage="369" CitTreatCitCount="1" CitFigCitCount="8" CitTabCitCount="3"/>
<statData DocCount="1" DocUuid="03C087A9FFC3382699EAFD9CFE9BD286" DocDoi="http://doi.org/10.5281/zenodo.4694764" DocArticleUuid="FFF9FFD1FFC23822997DFFDAFF9FD253" BibYear="2021" BibSource="Zootaxa" BibVolume="4952" BibIssue="2" BibFirstPage="392" BibLastPage="395" CitTreatCitCount="1" CitFigCitCount="3" CitTabCitCount="3"/>
<statData DocCount="1" DocUuid="E52787FFFFD4F74FFF4CDBB8FCBEDA84" DocDoi="http://doi.org/10.5281/zenodo.4432590" DocArticleUuid="191EFF87FFD5F745FFDBD84EFF81DB29" BibYear="2021" BibSource="Zootaxa" BibVolume="4903" BibIssue="3" BibFirstPage="394" BibLastPage="403" CitTreatCitCount="20" CitFigCitCount="52" CitTabCitCount="1"/>
<statData DocCount="1" DocUuid="039E87FEF56EE64AA7A0FAB493A7F876" DocDoi="http://doi.org/10.5281/zenodo.4478189" DocArticleUuid="FFA7FF86F56AE64FA737FFD7970AFFBC" BibYear="2021" BibSource="Zootaxa" BibVolume="4920" BibIssue="3" BibFirstPage="421" BibLastPage="422" CitTreatCitCount="3" CitFigCitCount="12" CitTabCitCount="1"/>
<statData DocCount="1" DocUuid="03A087ACE66C396604CADED1FBFCE7FD" DocDoi="http://doi.org/10.5281/zenodo.4669929" DocArticleUuid="FF99FFD4E66F3965045DDD02FFDFE00C" BibYear="2021" BibSource="Zootaxa" BibVolume="4948" BibIssue="3" BibFirstPage="422" BibLastPage="422" CitTreatCitCount="7" CitFigCitCount="2" CitTabCitCount="1"/>
<statData DocCount="1" DocUuid="039E87FEF56DE648A7A0FC219477FA24" DocDoi="http://doi.org/10.5281/zenodo.4478191" DocArticleUuid="FFA7FF86F56AE64FA737FFD7970AFFBC" BibYear="2021" BibSource="Zootaxa" BibVolume="4920" BibIssue="3" BibFirstPage="424" BibLastPage="424" CitTreatCitCount="1" CitFigCitCount="3" CitTabCitCount="1"/>
<statData DocCount="1" DocUuid="03D88782FFA92202FF7BF9071F6AFCEE" DocDoi="http://doi.org/10.5281/zenodo.4617027" DocArticleUuid="FFE1FFFAFFAB220AFFECFFA51C59FFB3" BibYear="2021" BibSource="Zootaxa" BibVolume="4941" BibIssue="4" BibFirstPage="453" BibLastPage="459" CitTreatCitCount="1" CitFigCitCount="4" CitTabCitCount="2"/>
<statData DocCount="1" DocUuid="A157FD05FFBF4B4CFF2FFBDFFC0F2236" DocDoi="http://doi.org/10.5281/zenodo.4558063" DocArticleUuid="5D6E857DFFBD4B45FFB8FFBDFF98266C" BibYear="2021" BibSource="Zootaxa" BibVolume="4926" BibIssue="4" BibFirstPage="453" BibLastPage="460" CitTreatCitCount="1" CitFigCitCount="42" CitTabCitCount="1"/>
<statData DocCount="1" DocUuid="BA5287F8FF9BFFF8FF16C5F7FC1FBCDC" DocDoi="http://doi.org/10.5281/zenodo.4694580" DocArticleUuid="466BFF80FF8BFFE9FF81C601FF96BD29" BibYear="2021" BibSource="Zootaxa" BibVolume="4950" BibIssue="3" BibFirstPage="457" BibLastPage="458" CitTreatCitCount="2" CitFigCitCount="9" CitTabCitCount="1"/>
<statData DocCount="1" DocUuid="BA5287F8FF9AFFFAFF16C0DFFF6CBF30" DocDoi="http://doi.org/10.5281/zenodo.4694582" DocArticleUuid="466BFF80FF8BFFE9FF81C601FF96BD29" BibYear="2021" BibSource="Zootaxa" BibVolume="4950" BibIssue="3" BibFirstPage="458" BibLastPage="460" CitTreatCitCount="1" CitFigCitCount="7" CitTabCitCount="1"/>
<statData DocCount="1" DocUuid="03D88782FFA32200FF7BFC0B1F6AFD36" DocDoi="http://doi.org/10.5281/zenodo.4617035" DocArticleUuid="FFE1FFFAFFAB220AFFECFFA51C59FFB3" BibYear="2021" BibSource="Zootaxa" BibVolume="4941" BibIssue="4" BibFirstPage="459" BibLastPage="461" CitTreatCitCount="1" CitFigCitCount="4" CitTabCitCount="3"/>
<statData DocCount="1" DocUuid="03D88782FFA12201FF7BFD731F22FD7E" DocDoi="http://doi.org/10.5281/zenodo.4595515" DocArticleUuid="FFE1FFFAFFAB220AFFECFFA51C59FFB3" BibYear="2021" BibSource="Zootaxa" BibVolume="4941" BibIssue="4" BibFirstPage="461" BibLastPage="462" CitTreatCitCount="1" CitFigCitCount="4" CitTabCitCount="2"/>
<statData DocCount="1" DocUuid="BA5287F8FF9DFFFEFF16C76EFC84BF15" DocDoi="http://doi.org/10.5281/zenodo.4694594" DocArticleUuid="466BFF80FF8BFFE9FF81C601FF96BD29" BibYear="2021" BibSource="Zootaxa" BibVolume="4950" BibIssue="3" BibFirstPage="463" BibLastPage="464" CitTreatCitCount="7" CitFigCitCount="10" CitTabCitCount="1"/>
<statData DocCount="1" DocUuid="03D88782FFA62207FF7BFF321DA8F835" DocDoi="http://doi.org/10.5281/zenodo.4617050" DocArticleUuid="FFE1FFFAFFAB220AFFECFFA51C59FFB3" BibYear="2021" BibSource="Zootaxa" BibVolume="4941" BibIssue="4" BibFirstPage="464" BibLastPage="464" CitTreatCitCount="1" CitFigCitCount="5" CitTabCitCount="2"/>
<statData DocCount="1" DocUuid="03D88782FFA52204FF7BFF321D4FF847" DocDoi="http://doi.org/10.5281/zenodo.4617054" DocArticleUuid="FFE1FFFAFFAB220AFFECFFA51C59FFB3" BibYear="2021" BibSource="Zootaxa" BibVolume="4941" BibIssue="4" BibFirstPage="465" BibLastPage="465" CitTreatCitCount="1" CitFigCitCount="5" CitTabCitCount="2"/>
<statData DocCount="1" DocUuid="A11D4862FFF3FF98FF79FF5C8718FCC5" DocDoi="http://doi.org/10.5281/zenodo.4647777" DocArticleUuid="5D24301AFFE6FF80FFEEFFCB8528FF9A" BibYear="2021" BibSource="Zootaxa" BibVolume="4949" BibIssue="3" BibFirstPage="466" BibLastPage="469" CitTreatCitCount="1" CitFigCitCount="82" CitTabCitCount="1"/>
<statData DocCount="1" DocUuid="A157FD05FFA84B5CFF2FFF2AFEFD2695" DocDoi="http://doi.org/10.5281/zenodo.4546096" DocArticleUuid="5D6E857DFFBD4B45FFB8FFBDFF98266C" BibYear="2021" BibSource="Zootaxa" BibVolume="4926" BibIssue="4" BibFirstPage="472" BibLastPage="475" CitTreatCitCount="2" CitFigCitCount="20" CitTabCitCount="1"/>
<statData DocCount="1" DocUuid="3660577CFFA5FF82E5B29471FB1CFC17" DocDoi="http://doi.org/10.5281/zenodo.4607480" DocArticleUuid="CA592F04FFA4FF87E5259314FFF6FF96" BibYear="2021" BibSource="Zootaxa" BibVolume="4938" BibIssue="4" BibFirstPage="476" BibLastPage="480" CitTreatCitCount="12" CitFigCitCount="25" CitTabCitCount="1"/>
<statData DocCount="1" DocUuid="3660577CFFA1FF8EE5B2952BFE6AF847" DocDoi="http://doi.org/10.5281/zenodo.4607484" DocArticleUuid="CA592F04FFA4FF87E5259314FFF6FF96" BibYear="2021" BibSource="Zootaxa" BibVolume="4938" BibIssue="4" BibFirstPage="480" BibLastPage="484" CitTreatCitCount="14" CitFigCitCount="25" CitTabCitCount="1"/>
<statData DocCount="1" DocUuid="038587F4682DFFF24E8D6615FE5BF9F5" DocDoi="http://doi.org/10.5281/zenodo.4711367" DocArticleUuid="FFBCFF8C6823FFE14E1A672FFFFDFF80" BibYear="2021" BibSource="Zootaxa" BibVolume="4958" BibIssue="1" BibFirstPage="524" BibLastPage="529" CitTreatCitCount="24" CitFigCitCount="48" CitTabCitCount="3"/>
<statData DocCount="1" DocUuid="038587F46803FFC04E8D6665FD01FC01" DocDoi="http://doi.org/10.5281/zenodo.4711373" DocArticleUuid="FFBCFF8C6823FFE14E1A672FFFFDFF80" BibYear="2021" BibSource="Zootaxa" BibVolume="4958" BibIssue="1" BibFirstPage="542" BibLastPage="543" CitTreatCitCount="6" CitFigCitCount="28" CitTabCitCount="2"/>
<statData DocCount="1" DocUuid="3011EC32FFB77913FF16ACBCFE79F3AE" DocDoi="http://doi.org/10.5281/zenodo.4670060" DocArticleUuid="CC28944AFFB47915FF81A816FFC6F513" BibYear="2021" BibSource="Zootaxa" BibVolume="4948" BibIssue="4" BibFirstPage="549" BibLastPage="552" CitTreatCitCount="8" CitFigCitCount="24" CitTabCitCount="1"/>
<statData DocCount="1" DocUuid="261DBB48FF83FFA2758FFF2CFEDEF862" DocDoi="http://doi.org/10.5281/zenodo.4685085" DocArticleUuid="DA24C330FF80FFA77518FFBBFFEBFFDF" BibYear="2021" BibSource="Zootaxa" BibVolume="4951" BibIssue="3" BibFirstPage="562" BibLastPage="564" CitTreatCitCount="2" CitFigCitCount="12" CitTabCitCount="1"/>
<statData DocCount="1" DocUuid="03BAAE1BFFB2FFA4FF6DFCAA57E1FB0D" DocDoi="http://doi.org/10.5281/zenodo.4727376" DocArticleUuid="FF83D663FFB5FFA3FFFAFFA5535FFFD9" BibYear="2021" BibSource="Zootaxa" BibVolume="4965" BibIssue="3" BibFirstPage="565" BibLastPage="565" CitTreatCitCount="1" CitFigCitCount="3" CitTabCitCount="1"/>
<statData DocCount="1" DocUuid="0F3DD06B6032FFF1FF477305FD88F9A9" DocDoi="http://doi.org/10.5281/zenodo.4531825" DocArticleUuid="F304A8136034FFFBFFD0745EFFA4FFA0" BibYear="2021" BibSource="Zootaxa" BibVolume="4920" BibIssue="4" BibFirstPage="571" BibLastPage="575" CitTreatCitCount="38" CitFigCitCount="18" CitTabCitCount="3"/>
<statData DocCount="1" DocUuid="0F3DD06B603EFFF6FF477213FDCCFDB9" DocDoi="http://doi.org/10.5281/zenodo.4531827" DocArticleUuid="F304A8136034FFFBFFD0745EFFA4FFA0" BibYear="2021" BibSource="Zootaxa" BibVolume="4920" BibIssue="4" BibFirstPage="575" BibLastPage="578" CitTreatCitCount="40" CitFigCitCount="14" CitTabCitCount="2"/>
<statData DocCount="1" DocUuid="03C287B40739FFE64CB8FECDFBA7E0CB" DocDoi="http://doi.org/10.5281/zenodo.4497809" DocArticleUuid="FFFBFFCC0738FFE34C2FFFA2FFF5E75E" BibYear="2021" BibSource="Zootaxa" BibVolume="4915" BibIssue="4" BibFirstPage="576" BibLastPage="580" CitTreatCitCount="17" CitFigCitCount="24" CitTabCitCount="1"/>
<statData DocCount="1" DocUuid="03A0721BFFB3FF94FF42BC8409CAFD60" DocDoi="http://doi.org/10.5281/zenodo.4546362" DocArticleUuid="FF990A63FFB0FF91FFD5BC130B6FFF91" BibYear="2021" BibSource="Zootaxa" BibVolume="4926" BibIssue="4" BibFirstPage="580" BibLastPage="582" CitTreatCitCount="2" CitFigCitCount="10" CitTabCitCount="1"/>
<statData DocCount="1" DocUuid="0F3DD06B6024FFE9FF4772FEFED4FE0D" DocDoi="http://doi.org/10.5281/zenodo.4491278" DocArticleUuid="F304A8136034FFFBFFD0745EFFA4FFA0" BibYear="2021" BibSource="Zootaxa" BibVolume="4920" BibIssue="4" BibFirstPage="581" BibLastPage="583" CitTreatCitCount="14" CitFigCitCount="11" CitTabCitCount="2"/>
<statData DocCount="1" DocUuid="03A0721BFFB5FF96FF42BA54082EFE18" DocDoi="http://doi.org/10.5281/zenodo.4529756" DocArticleUuid="FF990A63FFB0FF91FFD5BC130B6FFF91" BibYear="2021" BibSource="Zootaxa" BibVolume="4926" BibIssue="4" BibFirstPage="582" BibLastPage="583" CitTreatCitCount="1" CitFigCitCount="10" CitTabCitCount="1"/>
<statData DocCount="1" DocUuid="0F3DD06B6026FFEFFF47731EFD04FB65" DocDoi="http://doi.org/10.5281/zenodo.4531836" DocArticleUuid="F304A8136034FFFBFFD0745EFFA4FFA0" BibYear="2021" BibSource="Zootaxa" BibVolume="4920" BibIssue="4" BibFirstPage="583" BibLastPage="585" CitTreatCitCount="6" CitFigCitCount="16" CitTabCitCount="2"/>
<statData DocCount="1" DocUuid="03A0721BFFB7FF99FF42BA20090FFEF4" DocDoi="http://doi.org/10.5281/zenodo.4546364" DocArticleUuid="FF990A63FFB0FF91FFD5BC130B6FFF91" BibYear="2021" BibSource="Zootaxa" BibVolume="4926" BibIssue="4" BibFirstPage="584" BibLastPage="585" CitTreatCitCount="4" CitFigCitCount="2" CitTabCitCount="1"/>
</statistics>
