<?xml version="1.0" encoding="UTF-8"?>
<tp:taxon-treatment xmlns:tp="http://www.plazi.org/taxpub">
   <tp:nomenclature>
      <tp:taxon-name>
Tafana humahuaca
</tp:taxon-name>
sp. nov.
</tp:nomenclature>
   <tp:treatment-sec sec-type="materials_examined">
      <p>
ARGENTINA
• 
1 ♂
; 
Jujuy Province
, 
Santa Bárbara
; [
24°18′31″ S
; 
64°39′37″ W
]; 

Oct. 1969

; 
Williner
leg.; 
MACN-Ar 41787

• 

1 ♀
; 
Jujuy Province
, 
Santa Bárbara
; [
24°18′31″ S
; 
64°39′37″ W
]; 

Oct. 1962

; 
Williner
leg.; 
MACN-Ar 41788

.
</p>
   </tp:treatment-sec>
</tp:taxon-treatment>
