<?xml version="1.0" encoding="UTF-8"?>
<!DOCTYPE tp:taxon-treatment
  PUBLIC "-//TaxPub//DTD Taxonomic Treatment Publishing DTD v1.0 20180101//EN" "https://raw.githubusercontent.com/plazi/TaxPub/TaxPubJATS-blue/tax-treatment-NS0-v1.dtd">
<tp:taxon-treatment xmlns:tp="http://www.plazi.org/taxpub"><tp:treatment-meta><mixed-citation>Yeshwanth, H. M., Chérot, F. &amp; Henry, T. J. Sophianus alces Distant 1904</mixed-citation></tp:treatment-meta>
<tp:nomenclature><tp:taxon-name>Sophianus alces Distant, 1904<object-id/></tp:taxon-name><xref/></tp:nomenclature>
<tp:treatment-sec sec-type="description">
<p>
(
<xref rid="fig-22--151-264-1925-1949-">Figs. 5E</xref>
, 
<xref rid="fig-24--151-264-1912-1936-">7D</xref>
, 
<xref rid="fig-33--151-264-1862-1886-">16</xref>
F–I)
</p>
</tp:treatment-sec>
<tp:treatment-sec sec-type="reference_group">

<tp:nomenclature-citation-list>
<tp:taxon-name>Sophianus Distant, 1904: 486</tp:taxon-name>
(as new species, DV, head); Schuh 1995: 16 (catalogue), 2002–2013 (online catalogue).
</tp:nomenclature-citation-list>

</tp:treatment-sec>
<tp:treatment-sec sec-type="diagnosis">
<p>
Diagnosis
. Relatively large species, length 
3.1 mm
. Head black, ocelli reddish. First and second antennal segment black, third and fourth segment yellowish brown (dull flavous according to 
<xref rid="ref18010">Distant 1904</xref>
). Pronotum, mesoscutum, and major part of scutellum black; apex of scutellum yellowish. Hemelytra yellowish brown; bases of clavii darker, apices of coria and cunei brown (piceous according to 
<xref rid="ref18010">Distant 1904</xref>
). Legs reddish brown. Membrane hyaline. Pronotum distinctly punctate; hemelytra finely punctate. 
Male genitalia
as in 
<xref rid="fig-33--151-264-1862-1886-">Figs. 16</xref>
F–I. Detailed measurements in 
<xref>Table 1</xref>
.
</p>
</tp:treatment-sec>
<tp:treatment-sec sec-type="materials_examined">
<p>
Material examined.
<tp:material-citation>
<named-content content-type="collectingCountry">INDIA</named-content>
: 17³, 
<named-content content-type="collectingRegion">Karnataka</named-content>
, 
<named-content content-type="collectingMunicipality">Belghaum</named-content>
, 
<named-content content-type="location">Arbhavi</named-content>
, 
<named-content content-type="quantity">
<named-content content-type="elevation">595 m</named-content>
</named-content>
, 
<named-content content-type="geoCoordinate">
16 
<named-content content-type="superScript">°</named-content>
13.605’N
</named-content>
, 
<named-content content-type="geoCoordinate">
074 
<named-content content-type="superScript">°</named-content>
50.016’E
</named-content>
, 
<named-content content-type="date">
<named-content content-type="collectingDate">15.viii.2011</named-content>
</named-content>
, 
<named-content content-type="collectorName">Yeshwanth H. M.</named-content>
leg., at light; 2³, 
<named-content content-type="collectorName">Bangalore</named-content>
, 
<named-content content-type="collectionCode">GKVK</named-content>
</tp:material-citation>
, 
<tp:material-citation>
<named-content content-type="quantity">
<named-content content-type="elevation">930m</named-content>
</named-content>
, 
<named-content content-type="geoCoordinate">12º 58’ N</named-content>
, 
<named-content content-type="geoCoordinate">77º35’E</named-content>
, 
<named-content content-type="date">
<named-content content-type="collectingDate">24.xii.2012</named-content>
</named-content>
, 
<named-content content-type="collectorName">Yeshwanth H. M.</named-content>
leg, at light (
<named-content content-type="collectionCode">UASB</named-content>
)
</tp:material-citation>
.
</p>
</tp:treatment-sec>
<tp:treatment-sec sec-type="discussion">
<p>
Remarks
. A single specimen of this species was originally described from 
Sri Lanka
. In the present study, numerous additional specimens were collected from 
Karnataka
, 
India
.
</p>
</tp:treatment-sec>
<tp:treatment-sec sec-type="distribution">
<p>
Distribution
. 
India
(
Karnataka
) and 
Sri Lanka
</p>
</tp:treatment-sec>
<ref-list><ref id="ref18010"><mixed-citation>Distant, W. L. (1904) The Fauna of British India, Including Ceylan and Burma. Rhynchota. Vol. 2. Part 2. Taylor &amp; Francis, London, pp. 243 - 503.</mixed-citation></ref><ref id="ref18010"><mixed-citation>Distant, W. L. (1904) The Fauna of British India, Including Ceylan and Burma. Rhynchota. Vol. 2. Part 2. Taylor &amp; Francis, London, pp. 243 - 503.</mixed-citation></ref><ref id="ref18010"><mixed-citation>Distant, W. L. (1904) The Fauna of British India, Including Ceylan and Burma. Rhynchota. Vol. 2. Part 2. Taylor &amp; Francis, London, pp. 243 - 503.</mixed-citation></ref></ref-list></tp:taxon-treatment>