<?xml version="1.0" encoding="UTF-8"?>
<tp:taxon-treatment xmlns:tp="http://www.plazi.org/taxpub">
   <tp:nomenclature>
      <tp:taxon-name>
Acroterius camur
</tp:taxon-name>
gen. et sp. nov.
</tp:nomenclature>
   <tp:treatment-sec sec-type="description">
      <p>

urn:lsid:zoobank.org:act: 
B86B9669-F527-44A7-BAF0-40B777161195
</p>
      <p>
Figs 10–14
, 
38
</p>
   </tp:treatment-sec>
   <tp:treatment-sec sec-type="diagnosis">
      <p>
Differential diagnosis
</p>
      <p>
The new species resembles 
<tp:taxon-name>
Acroterius brevis
</tp:taxon-name>
gen. et sp. nov.
(
Figs 6A–D
, 
7A–B
) in having similar embolus in the male palp and a short parmula in the epigyne (
Figs 10A–D
, 
11A–D
, 
12A–B
) as in 
<tp:taxon-name>
A. inversus
</tp:taxon-name>
gen. et sp. nov.
and 
<tp:taxon-name>
A. longidentatus
</tp:taxon-name>
gen. et sp. nov.
; it can be distinguished by the distal arm of paracymbium with three projections and similar embolus, the radical thumb-shaped apophysis extends above the embolus in ventral view (
Figs 10D
, 
12A
), but is triangular and reaches to the base of the embolus in 
<tp:taxon-name>
A. brevis
</tp:taxon-name>
gen. et sp. nov.
(
Figs 6D
, 
7A
). Spermathecae hook-shaped, separated by one and half-length of spermathecae (
Fig. 13A–B
), but L-shaped and present near the posterior median plate in 
<tp:taxon-name>
A. brevis
</tp:taxon-name>
gen. et sp. nov.
(
Fig. 8A–D
). Parmula somewhat triangular (
Fig. 13A–D
), but tongue-shaped in 
<tp:taxon-name>
A. brevis
</tp:taxon-name>
gen. et sp. nov.
(
Fig. 8A–C
), anteriorly rectangular and posteriorly spoon-shaped in 
<tp:taxon-name>
A. inversus
</tp:taxon-name>
gen. et sp. nov.
(
Fig. 22A–C
), finger-shaped in 
<tp:taxon-name>
A. longidentatus
</tp:taxon-name>
gen. et sp. nov.
(
Fig. 29A–C
).
</p>
   </tp:treatment-sec>
   <tp:treatment-sec sec-type="etymology">
      <p>
Etymology
</p>
      <p>
The species name comes from the Latin adjective ‘ 
<tp:taxon-name>
camur
</tp:taxon-name>
’, meaning ‘curved’ and referring to the curved distal suprategular apophysis in the male palp.
</p>
   </tp:treatment-sec>
   <tp:treatment-sec sec-type="materials_examined">
      <p>
Type material
</p>
      <p>
Holotype
CHINA
• 
1 ♂
; 
Yunnan Province
, 
Gongshan County
, 
Bingzhongluo Township
, 
Niwaluo He
, 
just below Nujiang Road
; 
28.02499° N
, 
98.62564° E
; alt. 

1610 m

; 

8 Oct. 2002

; 
D.H. Kavanaugh
, 
P.E. Marek
and 
Hong-bin Liang
leg.; 
HNU-DHK–2002–038
.

</p>
      <p>
Paratypes

(
3 ♂♂
, 
23 ♀♀
)
</p>
      <p>
CHINA
– 

Yunnan Province

• 
2 ♂♂
, 
17 ♀♀
; same collection data as for holotype; 
HNU-DHK–2002–038

• 

1 ♀
; 
Cikai Township
, 
Dabadi
, 
North bank of Pula river
; 
27.78333° N
, 
98.51667° E
; alt. 

3030 m

; 

28 Sep. 2002

; 
Heng–mei
Yan
leg.; 
HNU-Yan020928

• 

1 ♀
; 
Cikai Township
, 
Dabadi to Gongshan, along Pula river downward
; 
27.7945833° N
, 
98.5071389° E
; alt. 

3025–3990 m

; 

4 Oct. 2002

; 
Heng
–mei 
Yan
leg.; 
HNU-Yan021004

• 

1 ♀
; 
Lushui County
, 
Waluoyaku
; 
25.78333° N
, 
98.78333° E
; alt. 

1070 m

; 

14 Oct. 2002

; 
Heng–mei
Yan
leg.; 
HNU-Yan021014

• 

2 ♀♀
; 
Tengchong County
, 
Wuhe Township
, 
Tongjia 12-dauzhuang Village
, 
Longchuanjiang River
(Longjiang bridge); 
24.89284° N
, 
98.67439° E
; alt. 

1210 m

; 

24 May 2005

; 
Heng-mei Yan
and 
Ke-ji Guo
leg.; 
HNU-GKJ020

• 

1 ♂
; 
Nujiang Prefecture
, 
Nujiang State Nature Reserve
, 
No. 12 bridge Camp area
, 

16.3 km
W of Gongshan

; 
27.71503° N
, 
98.50244° E
; alt. 

2775 m

; 

15–19 Jul. 2000

; 
Heng-mei Yan, D.H
. 
Kavanaugh
, 
Charles Griswold
, 
Hongbin Liang
, 
Darrell Ubick
and 
Da-zhi Dong
leg.; 
HNU-00–QD

• 

1 ♀
; 
Nujiang Prefecture
, 
Nujiang State Nature Reserve
, 
Dulong
/ 
Gongshan Yakou area
, 

21 km
W of Gongshan

; 
27.69655° N
, 
98.45389° E
; alt. 

3300–3680 m

; 

16–17 Jul. 2000

; 
Heng-mei Yan, D.H
. 
Kavanaugh
, 
Charles Griswold
, 
Hong-bin Liang
, 
Darrell Ubick
and 
Da-zhi Dong
leg.; 
HNU-00–BY

.
</p>
   </tp:treatment-sec>
   <tp:treatment-sec sec-type="description">
      <p>
Description
</p>
      <p>
Male
(
holotype
)
</p>
      <p>
MEASUREMENTS AND COLOUR. Total length: 2.95. Carapace 1.41 long, 1.14 wide, cephalothorax brown; clypeus 0.56 high (
Fig. 14A–B
); abdomen 1.54 long, 1.02 wide (
Fig. 14A–B
). Eye sizes and interdistances: AME 0.06, ALE 0.07, PME 0.07, PLE 0.07, AME–AME 0.04, PME–PME 0.06, AME– ALE 0.08, PME–PLE 0.07, ALE–ALE 0.42, PLE–PLE 0.46.
</p>
      <p>
Fig. 10.
<tp:taxon-name>
Acroterius camur
</tp:taxon-name>
gen. et sp. nov.
, ♂, holotype (HNU-DHK–2002–038), palp. 
A
. Prolateral view. 
B
. Retrolateral view. 
C
. Dorsal view. 
D
. Ventral view.
</p>
      <p>
Fig. 11.
<tp:taxon-name>
Acroterius camur
</tp:taxon-name>
gen. et sp. nov.
, ♂, holotype (HNU-DHK–2002–038). 
A–B
. Embolic division, ventral view. 
C
. Embolic division, prolateral view. 
D
. Embolic division, dorsal view.
</p>
      <p>
CHELICERAE. With five promarginal and five retromarginal teeth (
Fig. 14B
); proximal two teeth of reteromargin much longer than distal one.
</p>
      <p>LENGTH OF LEGS. I = 6.11 (1.65, 1.92, 1.59, 0.95), II = 5.43 (1.62, 1.58, 1.38, 0.85), III = 4.13 (1.19, 1.26, 1.05, 0.63), IV = 5.61 (1.58, 1.79, 1.32, 0.92). Leg formula I–IV–II–III.</p>
      <p>
PALP (
Figs 10A–D
, 
11A–D
, 
12A–B
). Paracymbium highly sclerotized, distal arm with two projections; lateral projection small, somewhat triangular; ventral projection small with blunt end (
Figs 10B
, 
12B
); distal suprategular apophysis long, robust, distal part slightly curved with pointed end (
Figs 10A–C
, 
12A–B
). Radical apophysis thumb-shaped with blunt end extending above the embolus in ventral view (
Figs 10A–D
, 
11A–D
, 
12A–B
). Embolus stout, short with pointed end (
Figs 10A–D
, 
11A–D
, 
12A–B
).
</p>
      <p>
Female
(HNU-DHK–2002–038)
</p>
      <p>
MEASUREMENTS AND COLOUR. Total length: 2.66. Carapace 1.17 long, 1.01 wide, cephalothorax brown; clypeus 0.24 high (
Fig. 14C–D
); abdomen 1.49 long, 1.21 wide (
Fig. 14C–D
). Eye sizes and interdistances: AME 0.05, ALE 0.09, PME 0.08, PLE 0.07, AME–AME 0.04, PME–PME 0.06, AME– ALE 0.06, PME–PLE 0.05, ALE–ALE 0.41, PLE–PLE 0.46, ALE–PLE contiguous.
</p>
      <p>
Fig. 12.
<tp:taxon-name>
Acroterius camur
</tp:taxon-name>
gen. et sp. nov.
, ♂, holotype (HNU-DHK–2002–038), palp. 
A
. Prolateral view. 
B
. Retrolateral view.
</p>
      <p>CHELICERAE. With five promarginal and six retromarginal teeth; proximal teeth of reteromargin are much longer than distal one.</p>
      <p>LENGTH OF LEGS. I = 4.73 (1.31, 1.54, 1.06, 0.82), II = 4.13 (1.28, 1.23, 1, 0.62), III = 3.45 (0.99, 1.07, 0.91, 0.48), IV = 4.41 (1.29, 1.32, 1.02, 0.78). Leg formula I–IV–II–III.</p>
      <p>
EPIGYNE. Parmula 0.21 long, 0.41 wide at base (
Fig. 13A–B
); the posterior margin of anterior wall of epigynal plate with a projection horizontal to anterior wall of epigynal plate margin in orientation (
Fig. 13A–B
). Spermathecae slender, distal part hook-shaped (
Fig. 13D
).
</p>
   </tp:treatment-sec>
   <tp:treatment-sec sec-type="distribution">
      <p>
Distribution
</p>
      <p>
China
(
Yunnan Province
, 
Fig. 38
).
</p>
   </tp:treatment-sec>
</tp:taxon-treatment>
